<?xml version="1.0" encoding="UTF-8"?>
<!-- generated: 2025-06-03T15:50:09+08:00 -->
<!-- generated by: qiujie [??] -->
<adag xmlns="http://pegasus.isi.edu/schema/DAX" xmlns:xsi="http://www.w3.org/2001/XMLSchema-instance" xsi:schemaLocation="http://pegasus.isi.edu/schema/DAX http://pegasus.isi.edu/schema/dax-2.1.xsd" version="2.1" count="1" index="0" name="test" jobCount="100" fileCount="0" childCount="98">
<!-- part 1: list of all referenced files (may be empty) -->
<!-- part 2: definition of all jobs (at least one) -->
  <job id="ID00000" namespace="CyberShake" name="ZipPSA" version="1.0" runtime="0.42">
    <uses file="PeakVals_FFI_0_1_ID00003.bsa" link="input" register="false" transfer="false" optional="false" type="data" size="216"/>
    <uses file="PeakVals_FFI_0_1_ID00005.bsa" link="input" register="false" transfer="false" optional="false" type="data" size="216"/>
    <uses file="PeakVals_FFI_0_1_ID00007.bsa" link="input" register="false" transfer="false" optional="false" type="data" size="216"/>
    <uses file="PeakVals_FFI_0_1_ID00009.bsa" link="input" register="false" transfer="false" optional="false" type="data" size="216"/>
    <uses file="PeakVals_FFI_0_1_ID00011.bsa" link="input" register="false" transfer="false" optional="false" type="data" size="216"/>
    <uses file="PeakVals_FFI_0_1_ID00013.bsa" link="input" register="false" transfer="false" optional="false" type="data" size="216"/>
    <uses file="PeakVals_FFI_0_1_ID00015.bsa" link="input" register="false" transfer="false" optional="false" type="data" size="216"/>
    <uses file="PeakVals_FFI_0_1_ID00017.bsa" link="input" register="false" transfer="false" optional="false" type="data" size="216"/>
    <uses file="PeakVals_FFI_0_1_ID00019.bsa" link="input" register="false" transfer="false" optional="false" type="data" size="216"/>
    <uses file="PeakVals_FFI_0_1_ID00021.bsa" link="input" register="false" transfer="false" optional="false" type="data" size="216"/>
    <uses file="PeakVals_FFI_0_1_ID00023.bsa" link="input" register="false" transfer="false" optional="false" type="data" size="216"/>
    <uses file="PeakVals_FFI_0_1_ID00025.bsa" link="input" register="false" transfer="false" optional="false" type="data" size="216"/>
    <uses file="PeakVals_FFI_0_1_ID00027.bsa" link="input" register="false" transfer="false" optional="false" type="data" size="216"/>
    <uses file="PeakVals_FFI_0_1_ID00029.bsa" link="input" register="false" transfer="false" optional="false" type="data" size="216"/>
    <uses file="PeakVals_FFI_0_1_ID00031.bsa" link="input" register="false" transfer="false" optional="false" type="data" size="216"/>
    <uses file="PeakVals_FFI_0_1_ID00033.bsa" link="input" register="false" transfer="false" optional="false" type="data" size="216"/>
    <uses file="PeakVals_FFI_0_1_ID00035.bsa" link="input" register="false" transfer="false" optional="false" type="data" size="216"/>
    <uses file="PeakVals_FFI_0_1_ID00037.bsa" link="input" register="false" transfer="false" optional="false" type="data" size="216"/>
    <uses file="PeakVals_FFI_0_1_ID00039.bsa" link="input" register="false" transfer="false" optional="false" type="data" size="216"/>
    <uses file="PeakVals_FFI_0_1_ID00041.bsa" link="input" register="false" transfer="false" optional="false" type="data" size="216"/>
    <uses file="PeakVals_FFI_0_1_ID00043.bsa" link="input" register="false" transfer="false" optional="false" type="data" size="216"/>
    <uses file="PeakVals_FFI_0_1_ID00045.bsa" link="input" register="false" transfer="false" optional="false" type="data" size="216"/>
    <uses file="PeakVals_FFI_0_1_ID00047.bsa" link="input" register="false" transfer="false" optional="false" type="data" size="216"/>
    <uses file="PeakVals_FFI_0_1_ID00049.bsa" link="input" register="false" transfer="false" optional="false" type="data" size="216"/>
    <uses file="PeakVals_FFI_1_0_ID00052.bsa" link="input" register="false" transfer="false" optional="false" type="data" size="216"/>
    <uses file="PeakVals_FFI_1_0_ID00054.bsa" link="input" register="false" transfer="false" optional="false" type="data" size="216"/>
    <uses file="PeakVals_FFI_1_0_ID00056.bsa" link="input" register="false" transfer="false" optional="false" type="data" size="216"/>
    <uses file="PeakVals_FFI_1_0_ID00058.bsa" link="input" register="false" transfer="false" optional="false" type="data" size="216"/>
    <uses file="PeakVals_FFI_1_0_ID00060.bsa" link="input" register="false" transfer="false" optional="false" type="data" size="216"/>
    <uses file="PeakVals_FFI_1_0_ID00062.bsa" link="input" register="false" transfer="false" optional="false" type="data" size="216"/>
    <uses file="PeakVals_FFI_1_0_ID00064.bsa" link="input" register="false" transfer="false" optional="false" type="data" size="216"/>
    <uses file="PeakVals_FFI_1_0_ID00066.bsa" link="input" register="false" transfer="false" optional="false" type="data" size="216"/>
    <uses file="PeakVals_FFI_1_0_ID00068.bsa" link="input" register="false" transfer="false" optional="false" type="data" size="216"/>
    <uses file="PeakVals_FFI_1_0_ID00070.bsa" link="input" register="false" transfer="false" optional="false" type="data" size="216"/>
    <uses file="PeakVals_FFI_1_0_ID00072.bsa" link="input" register="false" transfer="false" optional="false" type="data" size="216"/>
    <uses file="PeakVals_FFI_1_0_ID00074.bsa" link="input" register="false" transfer="false" optional="false" type="data" size="216"/>
    <uses file="PeakVals_FFI_1_0_ID00076.bsa" link="input" register="false" transfer="false" optional="false" type="data" size="216"/>
    <uses file="PeakVals_FFI_1_0_ID00078.bsa" link="input" register="false" transfer="false" optional="false" type="data" size="216"/>
    <uses file="PeakVals_FFI_1_0_ID00080.bsa" link="input" register="false" transfer="false" optional="false" type="data" size="216"/>
    <uses file="PeakVals_FFI_1_0_ID00082.bsa" link="input" register="false" transfer="false" optional="false" type="data" size="216"/>
    <uses file="PeakVals_FFI_1_0_ID00084.bsa" link="input" register="false" transfer="false" optional="false" type="data" size="216"/>
    <uses file="PeakVals_FFI_1_0_ID00086.bsa" link="input" register="false" transfer="false" optional="false" type="data" size="216"/>
    <uses file="PeakVals_FFI_1_0_ID00088.bsa" link="input" register="false" transfer="false" optional="false" type="data" size="216"/>
    <uses file="PeakVals_FFI_1_0_ID00090.bsa" link="input" register="false" transfer="false" optional="false" type="data" size="216"/>
    <uses file="PeakVals_FFI_1_0_ID00092.bsa" link="input" register="false" transfer="false" optional="false" type="data" size="216"/>
    <uses file="PeakVals_FFI_1_0_ID00094.bsa" link="input" register="false" transfer="false" optional="false" type="data" size="216"/>
    <uses file="PeakVals_FFI_1_0_ID00096.bsa" link="input" register="false" transfer="false" optional="false" type="data" size="216"/>
    <uses file="PeakVals_FFI_1_0_ID00098.bsa" link="input" register="false" transfer="false" optional="false" type="data" size="216"/>
    <uses file="Cybershake_PSA.zip" link="output" register="true" transfer="true" optional="false" type="data" size="1173"/>
  </job>
  <job id="ID00001" namespace="CyberShake" name="ZipSeis" version="1.0" runtime="0.50">
    <uses file="Seismogram_FFI_0_1_ID00003.grm" link="input" register="false" transfer="false" optional="false" type="data" size="24000"/>
    <uses file="Seismogram_FFI_0_1_ID00005.grm" link="input" register="false" transfer="false" optional="false" type="data" size="24000"/>
    <uses file="Seismogram_FFI_0_1_ID00007.grm" link="input" register="false" transfer="false" optional="false" type="data" size="24000"/>
    <uses file="Seismogram_FFI_0_1_ID00009.grm" link="input" register="false" transfer="false" optional="false" type="data" size="24000"/>
    <uses file="Seismogram_FFI_0_1_ID00011.grm" link="input" register="false" transfer="false" optional="false" type="data" size="24000"/>
    <uses file="Seismogram_FFI_0_1_ID00013.grm" link="input" register="false" transfer="false" optional="false" type="data" size="24000"/>
    <uses file="Seismogram_FFI_0_1_ID00015.grm" link="input" register="false" transfer="false" optional="false" type="data" size="24000"/>
    <uses file="Seismogram_FFI_0_1_ID00017.grm" link="input" register="false" transfer="false" optional="false" type="data" size="24000"/>
    <uses file="Seismogram_FFI_0_1_ID00019.grm" link="input" register="false" transfer="false" optional="false" type="data" size="24000"/>
    <uses file="Seismogram_FFI_0_1_ID00021.grm" link="input" register="false" transfer="false" optional="false" type="data" size="24000"/>
    <uses file="Seismogram_FFI_0_1_ID00023.grm" link="input" register="false" transfer="false" optional="false" type="data" size="24000"/>
    <uses file="Seismogram_FFI_0_1_ID00025.grm" link="input" register="false" transfer="false" optional="false" type="data" size="24000"/>
    <uses file="Seismogram_FFI_0_1_ID00027.grm" link="input" register="false" transfer="false" optional="false" type="data" size="24000"/>
    <uses file="Seismogram_FFI_0_1_ID00029.grm" link="input" register="false" transfer="false" optional="false" type="data" size="24000"/>
    <uses file="Seismogram_FFI_0_1_ID00031.grm" link="input" register="false" transfer="false" optional="false" type="data" size="24000"/>
    <uses file="Seismogram_FFI_0_1_ID00033.grm" link="input" register="false" transfer="false" optional="false" type="data" size="24000"/>
    <uses file="Seismogram_FFI_0_1_ID00035.grm" link="input" register="false" transfer="false" optional="false" type="data" size="24000"/>
    <uses file="Seismogram_FFI_0_1_ID00037.grm" link="input" register="false" transfer="false" optional="false" type="data" size="24000"/>
    <uses file="Seismogram_FFI_0_1_ID00039.grm" link="input" register="false" transfer="false" optional="false" type="data" size="24000"/>
    <uses file="Seismogram_FFI_0_1_ID00041.grm" link="input" register="false" transfer="false" optional="false" type="data" size="24000"/>
    <uses file="Seismogram_FFI_0_1_ID00043.grm" link="input" register="false" transfer="false" optional="false" type="data" size="24000"/>
    <uses file="Seismogram_FFI_0_1_ID00045.grm" link="input" register="false" transfer="false" optional="false" type="data" size="24000"/>
    <uses file="Seismogram_FFI_0_1_ID00047.grm" link="input" register="false" transfer="false" optional="false" type="data" size="24000"/>
    <uses file="Seismogram_FFI_0_1_ID00049.grm" link="input" register="false" transfer="false" optional="false" type="data" size="24000"/>
    <uses file="Seismogram_FFI_1_0_ID00052.grm" link="input" register="false" transfer="false" optional="false" type="data" size="24000"/>
    <uses file="Seismogram_FFI_1_0_ID00054.grm" link="input" register="false" transfer="false" optional="false" type="data" size="24000"/>
    <uses file="Seismogram_FFI_1_0_ID00056.grm" link="input" register="false" transfer="false" optional="false" type="data" size="24000"/>
    <uses file="Seismogram_FFI_1_0_ID00058.grm" link="input" register="false" transfer="false" optional="false" type="data" size="24000"/>
    <uses file="Seismogram_FFI_1_0_ID00060.grm" link="input" register="false" transfer="false" optional="false" type="data" size="24000"/>
    <uses file="Seismogram_FFI_1_0_ID00062.grm" link="input" register="false" transfer="false" optional="false" type="data" size="24000"/>
    <uses file="Seismogram_FFI_1_0_ID00064.grm" link="input" register="false" transfer="false" optional="false" type="data" size="24000"/>
    <uses file="Seismogram_FFI_1_0_ID00066.grm" link="input" register="false" transfer="false" optional="false" type="data" size="24000"/>
    <uses file="Seismogram_FFI_1_0_ID00068.grm" link="input" register="false" transfer="false" optional="false" type="data" size="24000"/>
    <uses file="Seismogram_FFI_1_0_ID00070.grm" link="input" register="false" transfer="false" optional="false" type="data" size="24000"/>
    <uses file="Seismogram_FFI_1_0_ID00072.grm" link="input" register="false" transfer="false" optional="false" type="data" size="24000"/>
    <uses file="Seismogram_FFI_1_0_ID00074.grm" link="input" register="false" transfer="false" optional="false" type="data" size="24000"/>
    <uses file="Seismogram_FFI_1_0_ID00076.grm" link="input" register="false" transfer="false" optional="false" type="data" size="24000"/>
    <uses file="Seismogram_FFI_1_0_ID00078.grm" link="input" register="false" transfer="false" optional="false" type="data" size="24000"/>
    <uses file="Seismogram_FFI_1_0_ID00080.grm" link="input" register="false" transfer="false" optional="false" type="data" size="24000"/>
    <uses file="Seismogram_FFI_1_0_ID00082.grm" link="input" register="false" transfer="false" optional="false" type="data" size="24000"/>
    <uses file="Seismogram_FFI_1_0_ID00084.grm" link="input" register="false" transfer="false" optional="false" type="data" size="24000"/>
    <uses file="Seismogram_FFI_1_0_ID00086.grm" link="input" register="false" transfer="false" optional="false" type="data" size="24000"/>
    <uses file="Seismogram_FFI_1_0_ID00088.grm" link="input" register="false" transfer="false" optional="false" type="data" size="24000"/>
    <uses file="Seismogram_FFI_1_0_ID00090.grm" link="input" register="false" transfer="false" optional="false" type="data" size="24000"/>
    <uses file="Seismogram_FFI_1_0_ID00092.grm" link="input" register="false" transfer="false" optional="false" type="data" size="24000"/>
    <uses file="Seismogram_FFI_1_0_ID00094.grm" link="input" register="false" transfer="false" optional="false" type="data" size="24000"/>
    <uses file="Seismogram_FFI_1_0_ID00096.grm" link="input" register="false" transfer="false" optional="false" type="data" size="24000"/>
    <uses file="Seismogram_FFI_1_0_ID00098.grm" link="input" register="false" transfer="false" optional="false" type="data" size="24000"/>
    <uses file="Cybershake_Seismograms.zip" link="output" register="true" transfer="true" optional="false" type="data" size="114885"/>
  </job>
  <job id="ID00002" namespace="CyberShake" name="ExtractSGT" version="1.0" runtime="151.62">
    <uses file="FFI_0_1_fx.sgt" link="input" register="true" transfer="true" optional="false" type="data" size="20078126574"/>
    <uses file="FFI_0_1_fy.sgt" link="input" register="true" transfer="true" optional="false" type="data" size="20078126574"/>
    <uses file="FFI_0_1_subfx.sgt" link="output" register="false" transfer="false" optional="false" type="data" size="133639615"/>
    <uses file="FFI_0_1_subfy.sgt" link="output" register="false" transfer="false" optional="false" type="data" size="133639615"/>
    <uses file="FFI_0_1_txt.variation-s01361-h08742" link="input" register="true" transfer="true" optional="false" type="data" size="3972857"/>
  </job>
  <job id="ID00003" namespace="CyberShake" name="SeismogramSynthesis" version="1.0" runtime="47.98">
    <uses file="FFI_0_1_txt.variation-s06101-h09955" link="input" register="true" transfer="true" optional="false" type="data" size="1904832"/>
    <uses file="FFI_0_1_subfx.sgt" link="input" register="false" transfer="false" optional="false" type="data" size="133639615"/>
    <uses file="FFI_0_1_subfy.sgt" link="input" register="false" transfer="false" optional="false" type="data" size="133639615"/>
    <uses file="Seismogram_FFI_0_1_ID00003.grm" link="output" register="false" transfer="false" optional="false" type="data" size="24000"/>
  </job>
  <job id="ID00004" namespace="CyberShake" name="PeakValCalcOkaya" version="1.0" runtime="1.19">
    <uses file="Seismogram_FFI_0_1_ID00003.grm" link="input" register="false" transfer="false" optional="false" type="data" size="24000"/>
    <uses file="PeakVals_FFI_0_1_ID00003.bsa" link="output" register="false" transfer="false" optional="false" type="data" size="216"/>
  </job>
  <job id="ID00005" namespace="CyberShake" name="SeismogramSynthesis" version="1.0" runtime="30.55">
    <uses file="FFI_0_1_txt.variation-s02739-h03338" link="input" register="true" transfer="true" optional="false" type="data" size="5182172"/>
    <uses file="FFI_0_1_subfx.sgt" link="input" register="false" transfer="false" optional="false" type="data" size="241189398"/>
    <uses file="FFI_0_1_subfy.sgt" link="input" register="false" transfer="false" optional="false" type="data" size="241189398"/>
    <uses file="Seismogram_FFI_0_1_ID00005.grm" link="output" register="false" transfer="false" optional="false" type="data" size="24000"/>
  </job>
  <job id="ID00006" namespace="CyberShake" name="PeakValCalcOkaya" version="1.0" runtime="1.41">
    <uses file="Seismogram_FFI_0_1_ID00005.grm" link="input" register="false" transfer="false" optional="false" type="data" size="24000"/>
    <uses file="PeakVals_FFI_0_1_ID00005.bsa" link="output" register="false" transfer="false" optional="false" type="data" size="216"/>
  </job>
  <job id="ID00007" namespace="CyberShake" name="SeismogramSynthesis" version="1.0" runtime="30.34">
    <uses file="FFI_0_1_txt.variation-s06362-h07228" link="input" register="true" transfer="true" optional="false" type="data" size="3307010"/>
    <uses file="FFI_0_1_subfx.sgt" link="input" register="false" transfer="false" optional="false" type="data" size="161096898"/>
    <uses file="FFI_0_1_subfy.sgt" link="input" register="false" transfer="false" optional="false" type="data" size="161096898"/>
    <uses file="Seismogram_FFI_0_1_ID00007.grm" link="output" register="false" transfer="false" optional="false" type="data" size="24000"/>
  </job>
  <job id="ID00008" namespace="CyberShake" name="PeakValCalcOkaya" version="1.0" runtime="1.61">
    <uses file="Seismogram_FFI_0_1_ID00007.grm" link="input" register="false" transfer="false" optional="false" type="data" size="24000"/>
    <uses file="PeakVals_FFI_0_1_ID00007.bsa" link="output" register="false" transfer="false" optional="false" type="data" size="216"/>
  </job>
  <job id="ID00009" namespace="CyberShake" name="SeismogramSynthesis" version="1.0" runtime="54.35">
    <uses file="FFI_0_1_txt.variation-s02251-h08047" link="input" register="true" transfer="true" optional="false" type="data" size="1957224"/>
    <uses file="FFI_0_1_subfx.sgt" link="input" register="false" transfer="false" optional="false" type="data" size="191637553"/>
    <uses file="FFI_0_1_subfy.sgt" link="input" register="false" transfer="false" optional="false" type="data" size="191637553"/>
    <uses file="Seismogram_FFI_0_1_ID00009.grm" link="output" register="false" transfer="false" optional="false" type="data" size="24000"/>
  </job>
  <job id="ID00010" namespace="CyberShake" name="PeakValCalcOkaya" version="1.0" runtime="0.89">
    <uses file="Seismogram_FFI_0_1_ID00009.grm" link="input" register="false" transfer="false" optional="false" type="data" size="24000"/>
    <uses file="PeakVals_FFI_0_1_ID00009.bsa" link="output" register="false" transfer="false" optional="false" type="data" size="216"/>
  </job>
  <job id="ID00011" namespace="CyberShake" name="SeismogramSynthesis" version="1.0" runtime="57.88">
    <uses file="FFI_0_1_txt.variation-s03184-h09810" link="input" register="true" transfer="true" optional="false" type="data" size="3798861"/>
    <uses file="FFI_0_1_subfx.sgt" link="input" register="false" transfer="false" optional="false" type="data" size="270868752"/>
    <uses file="FFI_0_1_subfy.sgt" link="input" register="false" transfer="false" optional="false" type="data" size="270868752"/>
    <uses file="Seismogram_FFI_0_1_ID00011.grm" link="output" register="false" transfer="false" optional="false" type="data" size="24000"/>
  </job>
  <job id="ID00012" namespace="CyberShake" name="PeakValCalcOkaya" version="1.0" runtime="1.24">
    <uses file="Seismogram_FFI_0_1_ID00011.grm" link="input" register="false" transfer="false" optional="false" type="data" size="24000"/>
    <uses file="PeakVals_FFI_0_1_ID00011.bsa" link="output" register="false" transfer="false" optional="false" type="data" size="216"/>
  </job>
  <job id="ID00013" namespace="CyberShake" name="SeismogramSynthesis" version="1.0" runtime="37.91">
    <uses file="FFI_0_1_txt.variation-s02204-h02398" link="input" register="true" transfer="true" optional="false" type="data" size="5173487"/>
    <uses file="FFI_0_1_subfx.sgt" link="input" register="false" transfer="false" optional="false" type="data" size="169082743"/>
    <uses file="FFI_0_1_subfy.sgt" link="input" register="false" transfer="false" optional="false" type="data" size="169082743"/>
    <uses file="Seismogram_FFI_0_1_ID00013.grm" link="output" register="false" transfer="false" optional="false" type="data" size="24000"/>
  </job>
  <job id="ID00014" namespace="CyberShake" name="PeakValCalcOkaya" version="1.0" runtime="1.45">
    <uses file="Seismogram_FFI_0_1_ID00013.grm" link="input" register="false" transfer="false" optional="false" type="data" size="24000"/>
    <uses file="PeakVals_FFI_0_1_ID00013.bsa" link="output" register="false" transfer="false" optional="false" type="data" size="216"/>
  </job>
  <job id="ID00015" namespace="CyberShake" name="SeismogramSynthesis" version="1.0" runtime="33.20">
    <uses file="FFI_0_1_txt.variation-s04595-h08741" link="input" register="true" transfer="true" optional="false" type="data" size="4967488"/>
    <uses file="FFI_0_1_subfx.sgt" link="input" register="false" transfer="false" optional="false" type="data" size="302462425"/>
    <uses file="FFI_0_1_subfy.sgt" link="input" register="false" transfer="false" optional="false" type="data" size="302462425"/>
    <uses file="Seismogram_FFI_0_1_ID00015.grm" link="output" register="false" transfer="false" optional="false" type="data" size="24000"/>
  </job>
  <job id="ID00016" namespace="CyberShake" name="PeakValCalcOkaya" version="1.0" runtime="0.69">
    <uses file="Seismogram_FFI_0_1_ID00015.grm" link="input" register="false" transfer="false" optional="false" type="data" size="24000"/>
    <uses file="PeakVals_FFI_0_1_ID00015.bsa" link="output" register="false" transfer="false" optional="false" type="data" size="216"/>
  </job>
  <job id="ID00017" namespace="CyberShake" name="SeismogramSynthesis" version="1.0" runtime="61.56">
    <uses file="FFI_0_1_txt.variation-s06865-h00597" link="input" register="true" transfer="true" optional="false" type="data" size="5344941"/>
    <uses file="FFI_0_1_subfx.sgt" link="input" register="false" transfer="false" optional="false" type="data" size="273940642"/>
    <uses file="FFI_0_1_subfy.sgt" link="input" register="false" transfer="false" optional="false" type="data" size="273940642"/>
    <uses file="Seismogram_FFI_0_1_ID00017.grm" link="output" register="false" transfer="false" optional="false" type="data" size="24000"/>
  </job>
  <job id="ID00018" namespace="CyberShake" name="PeakValCalcOkaya" version="1.0" runtime="1.23">
    <uses file="Seismogram_FFI_0_1_ID00017.grm" link="input" register="false" transfer="false" optional="false" type="data" size="24000"/>
    <uses file="PeakVals_FFI_0_1_ID00017.bsa" link="output" register="false" transfer="false" optional="false" type="data" size="216"/>
  </job>
  <job id="ID00019" namespace="CyberShake" name="SeismogramSynthesis" version="1.0" runtime="41.71">
    <uses file="FFI_0_1_txt.variation-s09022-h05068" link="input" register="true" transfer="true" optional="false" type="data" size="2176008"/>
    <uses file="FFI_0_1_subfx.sgt" link="input" register="false" transfer="false" optional="false" type="data" size="130223180"/>
    <uses file="FFI_0_1_subfy.sgt" link="input" register="false" transfer="false" optional="false" type="data" size="130223180"/>
    <uses file="Seismogram_FFI_0_1_ID00019.grm" link="output" register="false" transfer="false" optional="false" type="data" size="24000"/>
  </job>
  <job id="ID00020" namespace="CyberShake" name="PeakValCalcOkaya" version="1.0" runtime="1.21">
    <uses file="Seismogram_FFI_0_1_ID00019.grm" link="input" register="false" transfer="false" optional="false" type="data" size="24000"/>
    <uses file="PeakVals_FFI_0_1_ID00019.bsa" link="output" register="false" transfer="false" optional="false" type="data" size="216"/>
  </job>
  <job id="ID00021" namespace="CyberShake" name="SeismogramSynthesis" version="1.0" runtime="21.99">
    <uses file="FFI_0_1_txt.variation-s06210-h02490" link="input" register="true" transfer="true" optional="false" type="data" size="5050058"/>
    <uses file="FFI_0_1_subfx.sgt" link="input" register="false" transfer="false" optional="false" type="data" size="179221025"/>
    <uses file="FFI_0_1_subfy.sgt" link="input" register="false" transfer="false" optional="false" type="data" size="179221025"/>
    <uses file="Seismogram_FFI_0_1_ID00021.grm" link="output" register="false" transfer="false" optional="false" type="data" size="24000"/>
  </job>
  <job id="ID00022" namespace="CyberShake" name="PeakValCalcOkaya" version="1.0" runtime="0.86">
    <uses file="Seismogram_FFI_0_1_ID00021.grm" link="input" register="false" transfer="false" optional="false" type="data" size="24000"/>
    <uses file="PeakVals_FFI_0_1_ID00021.bsa" link="output" register="false" transfer="false" optional="false" type="data" size="216"/>
  </job>
  <job id="ID00023" namespace="CyberShake" name="SeismogramSynthesis" version="1.0" runtime="64.67">
    <uses file="FFI_0_1_txt.variation-s04142-h09434" link="input" register="true" transfer="true" optional="false" type="data" size="5100160"/>
    <uses file="FFI_0_1_subfx.sgt" link="input" register="false" transfer="false" optional="false" type="data" size="225740278"/>
    <uses file="FFI_0_1_subfy.sgt" link="input" register="false" transfer="false" optional="false" type="data" size="225740278"/>
    <uses file="Seismogram_FFI_0_1_ID00023.grm" link="output" register="false" transfer="false" optional="false" type="data" size="24000"/>
  </job>
  <job id="ID00024" namespace="CyberShake" name="PeakValCalcOkaya" version="1.0" runtime="0.86">
    <uses file="Seismogram_FFI_0_1_ID00023.grm" link="input" register="false" transfer="false" optional="false" type="data" size="24000"/>
    <uses file="PeakVals_FFI_0_1_ID00023.bsa" link="output" register="false" transfer="false" optional="false" type="data" size="216"/>
  </job>
  <job id="ID00025" namespace="CyberShake" name="SeismogramSynthesis" version="1.0" runtime="32.43">
    <uses file="FFI_0_1_txt.variation-s06030-h04318" link="input" register="true" transfer="true" optional="false" type="data" size="3310705"/>
    <uses file="FFI_0_1_subfx.sgt" link="input" register="false" transfer="false" optional="false" type="data" size="308799638"/>
    <uses file="FFI_0_1_subfy.sgt" link="input" register="false" transfer="false" optional="false" type="data" size="308799638"/>
    <uses file="Seismogram_FFI_0_1_ID00025.grm" link="output" register="false" transfer="false" optional="false" type="data" size="24000"/>
  </job>
  <job id="ID00026" namespace="CyberShake" name="PeakValCalcOkaya" version="1.0" runtime="1.13">
    <uses file="Seismogram_FFI_0_1_ID00025.grm" link="input" register="false" transfer="false" optional="false" type="data" size="24000"/>
    <uses file="PeakVals_FFI_0_1_ID00025.bsa" link="output" register="false" transfer="false" optional="false" type="data" size="216"/>
  </job>
  <job id="ID00027" namespace="CyberShake" name="SeismogramSynthesis" version="1.0" runtime="40.16">
    <uses file="FFI_0_1_txt.variation-s06736-h05022" link="input" register="true" transfer="true" optional="false" type="data" size="4808680"/>
    <uses file="FFI_0_1_subfx.sgt" link="input" register="false" transfer="false" optional="false" type="data" size="204112083"/>
    <uses file="FFI_0_1_subfy.sgt" link="input" register="false" transfer="false" optional="false" type="data" size="204112083"/>
    <uses file="Seismogram_FFI_0_1_ID00027.grm" link="output" register="false" transfer="false" optional="false" type="data" size="24000"/>
  </job>
  <job id="ID00028" namespace="CyberShake" name="PeakValCalcOkaya" version="1.0" runtime="1.19">
    <uses file="Seismogram_FFI_0_1_ID00027.grm" link="input" register="false" transfer="false" optional="false" type="data" size="24000"/>
    <uses file="PeakVals_FFI_0_1_ID00027.bsa" link="output" register="false" transfer="false" optional="false" type="data" size="216"/>
  </job>
  <job id="ID00029" namespace="CyberShake" name="SeismogramSynthesis" version="1.0" runtime="60.51">
    <uses file="FFI_0_1_txt.variation-s06566-h09662" link="input" register="true" transfer="true" optional="false" type="data" size="3185509"/>
    <uses file="FFI_0_1_subfx.sgt" link="input" register="false" transfer="false" optional="false" type="data" size="268399039"/>
    <uses file="FFI_0_1_subfy.sgt" link="input" register="false" transfer="false" optional="false" type="data" size="268399039"/>
    <uses file="Seismogram_FFI_0_1_ID00029.grm" link="output" register="false" transfer="false" optional="false" type="data" size="24000"/>
  </job>
  <job id="ID00030" namespace="CyberShake" name="PeakValCalcOkaya" version="1.0" runtime="0.89">
    <uses file="Seismogram_FFI_0_1_ID00029.grm" link="input" register="false" transfer="false" optional="false" type="data" size="24000"/>
    <uses file="PeakVals_FFI_0_1_ID00029.bsa" link="output" register="false" transfer="false" optional="false" type="data" size="216"/>
  </job>
  <job id="ID00031" namespace="CyberShake" name="SeismogramSynthesis" version="1.0" runtime="34.25">
    <uses file="FFI_0_1_txt.variation-s06681-h09546" link="input" register="true" transfer="true" optional="false" type="data" size="2077376"/>
    <uses file="FFI_0_1_subfx.sgt" link="input" register="false" transfer="false" optional="false" type="data" size="259675149"/>
    <uses file="FFI_0_1_subfy.sgt" link="input" register="false" transfer="false" optional="false" type="data" size="259675149"/>
    <uses file="Seismogram_FFI_0_1_ID00031.grm" link="output" register="false" transfer="false" optional="false" type="data" size="24000"/>
  </job>
  <job id="ID00032" namespace="CyberShake" name="PeakValCalcOkaya" version="1.0" runtime="0.78">
    <uses file="Seismogram_FFI_0_1_ID00031.grm" link="input" register="false" transfer="false" optional="false" type="data" size="24000"/>
    <uses file="PeakVals_FFI_0_1_ID00031.bsa" link="output" register="false" transfer="false" optional="false" type="data" size="216"/>
  </job>
  <job id="ID00033" namespace="CyberShake" name="SeismogramSynthesis" version="1.0" runtime="60.35">
    <uses file="FFI_0_1_txt.variation-s06591-h02388" link="input" register="true" transfer="true" optional="false" type="data" size="2160531"/>
    <uses file="FFI_0_1_subfx.sgt" link="input" register="false" transfer="false" optional="false" type="data" size="325861965"/>
    <uses file="FFI_0_1_subfy.sgt" link="input" register="false" transfer="false" optional="false" type="data" size="325861965"/>
    <uses file="Seismogram_FFI_0_1_ID00033.grm" link="output" register="false" transfer="false" optional="false" type="data" size="24000"/>
  </job>
  <job id="ID00034" namespace="CyberShake" name="PeakValCalcOkaya" version="1.0" runtime="1.30">
    <uses file="Seismogram_FFI_0_1_ID00033.grm" link="input" register="false" transfer="false" optional="false" type="data" size="24000"/>
    <uses file="PeakVals_FFI_0_1_ID00033.bsa" link="output" register="false" transfer="false" optional="false" type="data" size="216"/>
  </job>
  <job id="ID00035" namespace="CyberShake" name="SeismogramSynthesis" version="1.0" runtime="41.82">
    <uses file="FFI_0_1_txt.variation-s08927-h08447" link="input" register="true" transfer="true" optional="false" type="data" size="3095133"/>
    <uses file="FFI_0_1_subfx.sgt" link="input" register="false" transfer="false" optional="false" type="data" size="171529926"/>
    <uses file="FFI_0_1_subfy.sgt" link="input" register="false" transfer="false" optional="false" type="data" size="171529926"/>
    <uses file="Seismogram_FFI_0_1_ID00035.grm" link="output" register="false" transfer="false" optional="false" type="data" size="24000"/>
  </job>
  <job id="ID00036" namespace="CyberShake" name="PeakValCalcOkaya" version="1.0" runtime="1.45">
    <uses file="Seismogram_FFI_0_1_ID00035.grm" link="input" register="false" transfer="false" optional="false" type="data" size="24000"/>
    <uses file="PeakVals_FFI_0_1_ID00035.bsa" link="output" register="false" transfer="false" optional="false" type="data" size="216"/>
  </job>
  <job id="ID00037" namespace="CyberShake" name="SeismogramSynthesis" version="1.0" runtime="48.66">
    <uses file="FFI_0_1_txt.variation-s04793-h04104" link="input" register="true" transfer="true" optional="false" type="data" size="3427430"/>
    <uses file="FFI_0_1_subfx.sgt" link="input" register="false" transfer="false" optional="false" type="data" size="130933917"/>
    <uses file="FFI_0_1_subfy.sgt" link="input" register="false" transfer="false" optional="false" type="data" size="130933917"/>
    <uses file="Seismogram_FFI_0_1_ID00037.grm" link="output" register="false" transfer="false" optional="false" type="data" size="24000"/>
  </job>
  <job id="ID00038" namespace="CyberShake" name="PeakValCalcOkaya" version="1.0" runtime="0.62">
    <uses file="Seismogram_FFI_0_1_ID00037.grm" link="input" register="false" transfer="false" optional="false" type="data" size="24000"/>
    <uses file="PeakVals_FFI_0_1_ID00037.bsa" link="output" register="false" transfer="false" optional="false" type="data" size="216"/>
  </job>
  <job id="ID00039" namespace="CyberShake" name="SeismogramSynthesis" version="1.0" runtime="57.78">
    <uses file="FFI_0_1_txt.variation-s06249-h09602" link="input" register="true" transfer="true" optional="false" type="data" size="4749876"/>
    <uses file="FFI_0_1_subfx.sgt" link="input" register="false" transfer="false" optional="false" type="data" size="332247976"/>
    <uses file="FFI_0_1_subfy.sgt" link="input" register="false" transfer="false" optional="false" type="data" size="332247976"/>
    <uses file="Seismogram_FFI_0_1_ID00039.grm" link="output" register="false" transfer="false" optional="false" type="data" size="24000"/>
  </job>
  <job id="ID00040" namespace="CyberShake" name="PeakValCalcOkaya" version="1.0" runtime="0.65">
    <uses file="Seismogram_FFI_0_1_ID00039.grm" link="input" register="false" transfer="false" optional="false" type="data" size="24000"/>
    <uses file="PeakVals_FFI_0_1_ID00039.bsa" link="output" register="false" transfer="false" optional="false" type="data" size="216"/>
  </job>
  <job id="ID00041" namespace="CyberShake" name="SeismogramSynthesis" version="1.0" runtime="21.98">
    <uses file="FFI_0_1_txt.variation-s02023-h02469" link="input" register="true" transfer="true" optional="false" type="data" size="2797555"/>
    <uses file="FFI_0_1_subfx.sgt" link="input" register="false" transfer="false" optional="false" type="data" size="335792334"/>
    <uses file="FFI_0_1_subfy.sgt" link="input" register="false" transfer="false" optional="false" type="data" size="335792334"/>
    <uses file="Seismogram_FFI_0_1_ID00041.grm" link="output" register="false" transfer="false" optional="false" type="data" size="24000"/>
  </job>
  <job id="ID00042" namespace="CyberShake" name="PeakValCalcOkaya" version="1.0" runtime="0.76">
    <uses file="Seismogram_FFI_0_1_ID00041.grm" link="input" register="false" transfer="false" optional="false" type="data" size="24000"/>
    <uses file="PeakVals_FFI_0_1_ID00041.bsa" link="output" register="false" transfer="false" optional="false" type="data" size="216"/>
  </job>
  <job id="ID00043" namespace="CyberShake" name="SeismogramSynthesis" version="1.0" runtime="47.77">
    <uses file="FFI_0_1_txt.variation-s09847-h09746" link="input" register="true" transfer="true" optional="false" type="data" size="3426577"/>
    <uses file="FFI_0_1_subfx.sgt" link="input" register="false" transfer="false" optional="false" type="data" size="197896849"/>
    <uses file="FFI_0_1_subfy.sgt" link="input" register="false" transfer="false" optional="false" type="data" size="197896849"/>
    <uses file="Seismogram_FFI_0_1_ID00043.grm" link="output" register="false" transfer="false" optional="false" type="data" size="24000"/>
  </job>
  <job id="ID00044" namespace="CyberShake" name="PeakValCalcOkaya" version="1.0" runtime="1.46">
    <uses file="Seismogram_FFI_0_1_ID00043.grm" link="input" register="false" transfer="false" optional="false" type="data" size="24000"/>
    <uses file="PeakVals_FFI_0_1_ID00043.bsa" link="output" register="false" transfer="false" optional="false" type="data" size="216"/>
  </job>
  <job id="ID00045" namespace="CyberShake" name="SeismogramSynthesis" version="1.0" runtime="26.87">
    <uses file="FFI_0_1_txt.variation-s00287-h07783" link="input" register="true" transfer="true" optional="false" type="data" size="3594221"/>
    <uses file="FFI_0_1_subfx.sgt" link="input" register="false" transfer="false" optional="false" type="data" size="295345131"/>
    <uses file="FFI_0_1_subfy.sgt" link="input" register="false" transfer="false" optional="false" type="data" size="295345131"/>
    <uses file="Seismogram_FFI_0_1_ID00045.grm" link="output" register="false" transfer="false" optional="false" type="data" size="24000"/>
  </job>
  <job id="ID00046" namespace="CyberShake" name="PeakValCalcOkaya" version="1.0" runtime="1.24">
    <uses file="Seismogram_FFI_0_1_ID00045.grm" link="input" register="false" transfer="false" optional="false" type="data" size="24000"/>
    <uses file="PeakVals_FFI_0_1_ID00045.bsa" link="output" register="false" transfer="false" optional="false" type="data" size="216"/>
  </job>
  <job id="ID00047" namespace="CyberShake" name="SeismogramSynthesis" version="1.0" runtime="64.07">
    <uses file="FFI_0_1_txt.variation-s01242-h03731" link="input" register="true" transfer="true" optional="false" type="data" size="4455746"/>
    <uses file="FFI_0_1_subfx.sgt" link="input" register="false" transfer="false" optional="false" type="data" size="214525886"/>
    <uses file="FFI_0_1_subfy.sgt" link="input" register="false" transfer="false" optional="false" type="data" size="214525886"/>
    <uses file="Seismogram_FFI_0_1_ID00047.grm" link="output" register="false" transfer="false" optional="false" type="data" size="24000"/>
  </job>
  <job id="ID00048" namespace="CyberShake" name="PeakValCalcOkaya" version="1.0" runtime="1.53">
    <uses file="Seismogram_FFI_0_1_ID00047.grm" link="input" register="false" transfer="false" optional="false" type="data" size="24000"/>
    <uses file="PeakVals_FFI_0_1_ID00047.bsa" link="output" register="false" transfer="false" optional="false" type="data" size="216"/>
  </job>
  <job id="ID00049" namespace="CyberShake" name="SeismogramSynthesis" version="1.0" runtime="36.61">
    <uses file="FFI_0_1_txt.variation-s01361-h08742" link="input" register="true" transfer="true" optional="false" type="data" size="3972857"/>
    <uses file="FFI_0_1_subfx.sgt" link="input" register="false" transfer="false" optional="false" type="data" size="156787474"/>
    <uses file="FFI_0_1_subfy.sgt" link="input" register="false" transfer="false" optional="false" type="data" size="156787474"/>
    <uses file="Seismogram_FFI_0_1_ID00049.grm" link="output" register="false" transfer="false" optional="false" type="data" size="24000"/>
  </job>
  <job id="ID00050" namespace="CyberShake" name="PeakValCalcOkaya" version="1.0" runtime="1.58">
    <uses file="Seismogram_FFI_0_1_ID00049.grm" link="input" register="false" transfer="false" optional="false" type="data" size="24000"/>
    <uses file="PeakVals_FFI_0_1_ID00049.bsa" link="output" register="false" transfer="false" optional="false" type="data" size="216"/>
  </job>
  <job id="ID00051" namespace="CyberShake" name="ExtractSGT" version="1.0" runtime="74.47">
    <uses file="FFI_1_0_fx.sgt" link="input" register="true" transfer="true" optional="false" type="data" size="20530317166"/>
    <uses file="FFI_1_0_fy.sgt" link="input" register="true" transfer="true" optional="false" type="data" size="20530317166"/>
    <uses file="FFI_1_0_subfx.sgt" link="output" register="false" transfer="false" optional="false" type="data" size="263500602"/>
    <uses file="FFI_1_0_subfy.sgt" link="output" register="false" transfer="false" optional="false" type="data" size="263500602"/>
    <uses file="FFI_1_0_txt.variation-s01617-h01951" link="input" register="true" transfer="true" optional="false" type="data" size="2825284"/>
  </job>
  <job id="ID00052" namespace="CyberShake" name="SeismogramSynthesis" version="1.0" runtime="42.15">
    <uses file="FFI_1_0_txt.variation-s09181-h02351" link="input" register="true" transfer="true" optional="false" type="data" size="4496996"/>
    <uses file="FFI_1_0_subfx.sgt" link="input" register="false" transfer="false" optional="false" type="data" size="263500602"/>
    <uses file="FFI_1_0_subfy.sgt" link="input" register="false" transfer="false" optional="false" type="data" size="263500602"/>
    <uses file="Seismogram_FFI_1_0_ID00052.grm" link="output" register="false" transfer="false" optional="false" type="data" size="24000"/>
  </job>
  <job id="ID00053" namespace="CyberShake" name="PeakValCalcOkaya" version="1.0" runtime="1.44">
    <uses file="Seismogram_FFI_1_0_ID00052.grm" link="input" register="false" transfer="false" optional="false" type="data" size="24000"/>
    <uses file="PeakVals_FFI_1_0_ID00052.bsa" link="output" register="false" transfer="false" optional="false" type="data" size="216"/>
  </job>
  <job id="ID00054" namespace="CyberShake" name="SeismogramSynthesis" version="1.0" runtime="35.82">
    <uses file="FFI_1_0_txt.variation-s02245-h06583" link="input" register="true" transfer="true" optional="false" type="data" size="3728164"/>
    <uses file="FFI_1_0_subfx.sgt" link="input" register="false" transfer="false" optional="false" type="data" size="275146016"/>
    <uses file="FFI_1_0_subfy.sgt" link="input" register="false" transfer="false" optional="false" type="data" size="275146016"/>
    <uses file="Seismogram_FFI_1_0_ID00054.grm" link="output" register="false" transfer="false" optional="false" type="data" size="24000"/>
  </job>
  <job id="ID00055" namespace="CyberShake" name="PeakValCalcOkaya" version="1.0" runtime="0.81">
    <uses file="Seismogram_FFI_1_0_ID00054.grm" link="input" register="false" transfer="false" optional="false" type="data" size="24000"/>
    <uses file="PeakVals_FFI_1_0_ID00054.bsa" link="output" register="false" transfer="false" optional="false" type="data" size="216"/>
  </job>
  <job id="ID00056" namespace="CyberShake" name="SeismogramSynthesis" version="1.0" runtime="50.56">
    <uses file="FFI_1_0_txt.variation-s05171-h04625" link="input" register="true" transfer="true" optional="false" type="data" size="3345455"/>
    <uses file="FFI_1_0_subfx.sgt" link="input" register="false" transfer="false" optional="false" type="data" size="318818573"/>
    <uses file="FFI_1_0_subfy.sgt" link="input" register="false" transfer="false" optional="false" type="data" size="318818573"/>
    <uses file="Seismogram_FFI_1_0_ID00056.grm" link="output" register="false" transfer="false" optional="false" type="data" size="24000"/>
  </job>
  <job id="ID00057" namespace="CyberShake" name="PeakValCalcOkaya" version="1.0" runtime="0.98">
    <uses file="Seismogram_FFI_1_0_ID00056.grm" link="input" register="false" transfer="false" optional="false" type="data" size="24000"/>
    <uses file="PeakVals_FFI_1_0_ID00056.bsa" link="output" register="false" transfer="false" optional="false" type="data" size="216"/>
  </job>
  <job id="ID00058" namespace="CyberShake" name="SeismogramSynthesis" version="1.0" runtime="27.48">
    <uses file="FFI_1_0_txt.variation-s04568-h03339" link="input" register="true" transfer="true" optional="false" type="data" size="2294760"/>
    <uses file="FFI_1_0_subfx.sgt" link="input" register="false" transfer="false" optional="false" type="data" size="163872786"/>
    <uses file="FFI_1_0_subfy.sgt" link="input" register="false" transfer="false" optional="false" type="data" size="163872786"/>
    <uses file="Seismogram_FFI_1_0_ID00058.grm" link="output" register="false" transfer="false" optional="false" type="data" size="24000"/>
  </job>
  <job id="ID00059" namespace="CyberShake" name="PeakValCalcOkaya" version="1.0" runtime="1.23">
    <uses file="Seismogram_FFI_1_0_ID00058.grm" link="input" register="false" transfer="false" optional="false" type="data" size="24000"/>
    <uses file="PeakVals_FFI_1_0_ID00058.bsa" link="output" register="false" transfer="false" optional="false" type="data" size="216"/>
  </job>
  <job id="ID00060" namespace="CyberShake" name="SeismogramSynthesis" version="1.0" runtime="24.08">
    <uses file="FFI_1_0_txt.variation-s07098-h09146" link="input" register="true" transfer="true" optional="false" type="data" size="3359951"/>
    <uses file="FFI_1_0_subfx.sgt" link="input" register="false" transfer="false" optional="false" type="data" size="321104963"/>
    <uses file="FFI_1_0_subfy.sgt" link="input" register="false" transfer="false" optional="false" type="data" size="321104963"/>
    <uses file="Seismogram_FFI_1_0_ID00060.grm" link="output" register="false" transfer="false" optional="false" type="data" size="24000"/>
  </job>
  <job id="ID00061" namespace="CyberShake" name="PeakValCalcOkaya" version="1.0" runtime="1.30">
    <uses file="Seismogram_FFI_1_0_ID00060.grm" link="input" register="false" transfer="false" optional="false" type="data" size="24000"/>
    <uses file="PeakVals_FFI_1_0_ID00060.bsa" link="output" register="false" transfer="false" optional="false" type="data" size="216"/>
  </job>
  <job id="ID00062" namespace="CyberShake" name="SeismogramSynthesis" version="1.0" runtime="36.64">
    <uses file="FFI_1_0_txt.variation-s00334-h01484" link="input" register="true" transfer="true" optional="false" type="data" size="2210002"/>
    <uses file="FFI_1_0_subfx.sgt" link="input" register="false" transfer="false" optional="false" type="data" size="338410559"/>
    <uses file="FFI_1_0_subfy.sgt" link="input" register="false" transfer="false" optional="false" type="data" size="338410559"/>
    <uses file="Seismogram_FFI_1_0_ID00062.grm" link="output" register="false" transfer="false" optional="false" type="data" size="24000"/>
  </job>
  <job id="ID00063" namespace="CyberShake" name="PeakValCalcOkaya" version="1.0" runtime="1.38">
    <uses file="Seismogram_FFI_1_0_ID00062.grm" link="input" register="false" transfer="false" optional="false" type="data" size="24000"/>
    <uses file="PeakVals_FFI_1_0_ID00062.bsa" link="output" register="false" transfer="false" optional="false" type="data" size="216"/>
  </job>
  <job id="ID00064" namespace="CyberShake" name="SeismogramSynthesis" version="1.0" runtime="47.05">
    <uses file="FFI_1_0_txt.variation-s04989-h08317" link="input" register="true" transfer="true" optional="false" type="data" size="3343029"/>
    <uses file="FFI_1_0_subfx.sgt" link="input" register="false" transfer="false" optional="false" type="data" size="178433143"/>
    <uses file="FFI_1_0_subfy.sgt" link="input" register="false" transfer="false" optional="false" type="data" size="178433143"/>
    <uses file="Seismogram_FFI_1_0_ID00064.grm" link="output" register="false" transfer="false" optional="false" type="data" size="24000"/>
  </job>
  <job id="ID00065" namespace="CyberShake" name="PeakValCalcOkaya" version="1.0" runtime="0.82">
    <uses file="Seismogram_FFI_1_0_ID00064.grm" link="input" register="false" transfer="false" optional="false" type="data" size="24000"/>
    <uses file="PeakVals_FFI_1_0_ID00064.bsa" link="output" register="false" transfer="false" optional="false" type="data" size="216"/>
  </job>
  <job id="ID00066" namespace="CyberShake" name="SeismogramSynthesis" version="1.0" runtime="33.41">
    <uses file="FFI_1_0_txt.variation-s08842-h05449" link="input" register="true" transfer="true" optional="false" type="data" size="2053530"/>
    <uses file="FFI_1_0_subfx.sgt" link="input" register="false" transfer="false" optional="false" type="data" size="173346775"/>
    <uses file="FFI_1_0_subfy.sgt" link="input" register="false" transfer="false" optional="false" type="data" size="173346775"/>
    <uses file="Seismogram_FFI_1_0_ID00066.grm" link="output" register="false" transfer="false" optional="false" type="data" size="24000"/>
  </job>
  <job id="ID00067" namespace="CyberShake" name="PeakValCalcOkaya" version="1.0" runtime="1.47">
    <uses file="Seismogram_FFI_1_0_ID00066.grm" link="input" register="false" transfer="false" optional="false" type="data" size="24000"/>
    <uses file="PeakVals_FFI_1_0_ID00066.bsa" link="output" register="false" transfer="false" optional="false" type="data" size="216"/>
  </job>
  <job id="ID00068" namespace="CyberShake" name="SeismogramSynthesis" version="1.0" runtime="38.24">
    <uses file="FFI_1_0_txt.variation-s05744-h08232" link="input" register="true" transfer="true" optional="false" type="data" size="3083530"/>
    <uses file="FFI_1_0_subfx.sgt" link="input" register="false" transfer="false" optional="false" type="data" size="199665423"/>
    <uses file="FFI_1_0_subfy.sgt" link="input" register="false" transfer="false" optional="false" type="data" size="199665423"/>
    <uses file="Seismogram_FFI_1_0_ID00068.grm" link="output" register="false" transfer="false" optional="false" type="data" size="24000"/>
  </job>
  <job id="ID00069" namespace="CyberShake" name="PeakValCalcOkaya" version="1.0" runtime="1.44">
    <uses file="Seismogram_FFI_1_0_ID00068.grm" link="input" register="false" transfer="false" optional="false" type="data" size="24000"/>
    <uses file="PeakVals_FFI_1_0_ID00068.bsa" link="output" register="false" transfer="false" optional="false" type="data" size="216"/>
  </job>
  <job id="ID00070" namespace="CyberShake" name="SeismogramSynthesis" version="1.0" runtime="54.76">
    <uses file="FFI_1_0_txt.variation-s01869-h02189" link="input" register="true" transfer="true" optional="false" type="data" size="3417753"/>
    <uses file="FFI_1_0_subfx.sgt" link="input" register="false" transfer="false" optional="false" type="data" size="196528437"/>
    <uses file="FFI_1_0_subfy.sgt" link="input" register="false" transfer="false" optional="false" type="data" size="196528437"/>
    <uses file="Seismogram_FFI_1_0_ID00070.grm" link="output" register="false" transfer="false" optional="false" type="data" size="24000"/>
  </job>
  <job id="ID00071" namespace="CyberShake" name="PeakValCalcOkaya" version="1.0" runtime="1.16">
    <uses file="Seismogram_FFI_1_0_ID00070.grm" link="input" register="false" transfer="false" optional="false" type="data" size="24000"/>
    <uses file="PeakVals_FFI_1_0_ID00070.bsa" link="output" register="false" transfer="false" optional="false" type="data" size="216"/>
  </job>
  <job id="ID00072" namespace="CyberShake" name="SeismogramSynthesis" version="1.0" runtime="49.91">
    <uses file="FFI_1_0_txt.variation-s06986-h08446" link="input" register="true" transfer="true" optional="false" type="data" size="4038775"/>
    <uses file="FFI_1_0_subfx.sgt" link="input" register="false" transfer="false" optional="false" type="data" size="201116634"/>
    <uses file="FFI_1_0_subfy.sgt" link="input" register="false" transfer="false" optional="false" type="data" size="201116634"/>
    <uses file="Seismogram_FFI_1_0_ID00072.grm" link="output" register="false" transfer="false" optional="false" type="data" size="24000"/>
  </job>
  <job id="ID00073" namespace="CyberShake" name="PeakValCalcOkaya" version="1.0" runtime="1.29">
    <uses file="Seismogram_FFI_1_0_ID00072.grm" link="input" register="false" transfer="false" optional="false" type="data" size="24000"/>
    <uses file="PeakVals_FFI_1_0_ID00072.bsa" link="output" register="false" transfer="false" optional="false" type="data" size="216"/>
  </job>
  <job id="ID00074" namespace="CyberShake" name="SeismogramSynthesis" version="1.0" runtime="53.73">
    <uses file="FFI_1_0_txt.variation-s04073-h03303" link="input" register="true" transfer="true" optional="false" type="data" size="3319846"/>
    <uses file="FFI_1_0_subfx.sgt" link="input" register="false" transfer="false" optional="false" type="data" size="291266174"/>
    <uses file="FFI_1_0_subfy.sgt" link="input" register="false" transfer="false" optional="false" type="data" size="291266174"/>
    <uses file="Seismogram_FFI_1_0_ID00074.grm" link="output" register="false" transfer="false" optional="false" type="data" size="24000"/>
  </job>
  <job id="ID00075" namespace="CyberShake" name="PeakValCalcOkaya" version="1.0" runtime="0.76">
    <uses file="Seismogram_FFI_1_0_ID00074.grm" link="input" register="false" transfer="false" optional="false" type="data" size="24000"/>
    <uses file="PeakVals_FFI_1_0_ID00074.bsa" link="output" register="false" transfer="false" optional="false" type="data" size="216"/>
  </job>
  <job id="ID00076" namespace="CyberShake" name="SeismogramSynthesis" version="1.0" runtime="24.84">
    <uses file="FFI_1_0_txt.variation-s03666-h01295" link="input" register="true" transfer="true" optional="false" type="data" size="4402305"/>
    <uses file="FFI_1_0_subfx.sgt" link="input" register="false" transfer="false" optional="false" type="data" size="182160474"/>
    <uses file="FFI_1_0_subfy.sgt" link="input" register="false" transfer="false" optional="false" type="data" size="182160474"/>
    <uses file="Seismogram_FFI_1_0_ID00076.grm" link="output" register="false" transfer="false" optional="false" type="data" size="24000"/>
  </job>
  <job id="ID00077" namespace="CyberShake" name="PeakValCalcOkaya" version="1.0" runtime="0.81">
    <uses file="Seismogram_FFI_1_0_ID00076.grm" link="input" register="false" transfer="false" optional="false" type="data" size="24000"/>
    <uses file="PeakVals_FFI_1_0_ID00076.bsa" link="output" register="false" transfer="false" optional="false" type="data" size="216"/>
  </job>
  <job id="ID00078" namespace="CyberShake" name="SeismogramSynthesis" version="1.0" runtime="38.45">
    <uses file="FFI_1_0_txt.variation-s08451-h02556" link="input" register="true" transfer="true" optional="false" type="data" size="2051204"/>
    <uses file="FFI_1_0_subfx.sgt" link="input" register="false" transfer="false" optional="false" type="data" size="260787500"/>
    <uses file="FFI_1_0_subfy.sgt" link="input" register="false" transfer="false" optional="false" type="data" size="260787500"/>
    <uses file="Seismogram_FFI_1_0_ID00078.grm" link="output" register="false" transfer="false" optional="false" type="data" size="24000"/>
  </job>
  <job id="ID00079" namespace="CyberShake" name="PeakValCalcOkaya" version="1.0" runtime="1.52">
    <uses file="Seismogram_FFI_1_0_ID00078.grm" link="input" register="false" transfer="false" optional="false" type="data" size="24000"/>
    <uses file="PeakVals_FFI_1_0_ID00078.bsa" link="output" register="false" transfer="false" optional="false" type="data" size="216"/>
  </job>
  <job id="ID00080" namespace="CyberShake" name="SeismogramSynthesis" version="1.0" runtime="50.68">
    <uses file="FFI_1_0_txt.variation-s03415-h01024" link="input" register="true" transfer="true" optional="false" type="data" size="4669873"/>
    <uses file="FFI_1_0_subfx.sgt" link="input" register="false" transfer="false" optional="false" type="data" size="246124674"/>
    <uses file="FFI_1_0_subfy.sgt" link="input" register="false" transfer="false" optional="false" type="data" size="246124674"/>
    <uses file="Seismogram_FFI_1_0_ID00080.grm" link="output" register="false" transfer="false" optional="false" type="data" size="24000"/>
  </job>
  <job id="ID00081" namespace="CyberShake" name="PeakValCalcOkaya" version="1.0" runtime="1.34">
    <uses file="Seismogram_FFI_1_0_ID00080.grm" link="input" register="false" transfer="false" optional="false" type="data" size="24000"/>
    <uses file="PeakVals_FFI_1_0_ID00080.bsa" link="output" register="false" transfer="false" optional="false" type="data" size="216"/>
  </job>
  <job id="ID00082" namespace="CyberShake" name="SeismogramSynthesis" version="1.0" runtime="52.54">
    <uses file="FFI_1_0_txt.variation-s00465-h04979" link="input" register="true" transfer="true" optional="false" type="data" size="2354297"/>
    <uses file="FFI_1_0_subfx.sgt" link="input" register="false" transfer="false" optional="false" type="data" size="216302818"/>
    <uses file="FFI_1_0_subfy.sgt" link="input" register="false" transfer="false" optional="false" type="data" size="216302818"/>
    <uses file="Seismogram_FFI_1_0_ID00082.grm" link="output" register="false" transfer="false" optional="false" type="data" size="24000"/>
  </job>
  <job id="ID00083" namespace="CyberShake" name="PeakValCalcOkaya" version="1.0" runtime="1.43">
    <uses file="Seismogram_FFI_1_0_ID00082.grm" link="input" register="false" transfer="false" optional="false" type="data" size="24000"/>
    <uses file="PeakVals_FFI_1_0_ID00082.bsa" link="output" register="false" transfer="false" optional="false" type="data" size="216"/>
  </job>
  <job id="ID00084" namespace="CyberShake" name="SeismogramSynthesis" version="1.0" runtime="45.88">
    <uses file="FFI_1_0_txt.variation-s09672-h09639" link="input" register="true" transfer="true" optional="false" type="data" size="4144069"/>
    <uses file="FFI_1_0_subfx.sgt" link="input" register="false" transfer="false" optional="false" type="data" size="256969254"/>
    <uses file="FFI_1_0_subfy.sgt" link="input" register="false" transfer="false" optional="false" type="data" size="256969254"/>
    <uses file="Seismogram_FFI_1_0_ID00084.grm" link="output" register="false" transfer="false" optional="false" type="data" size="24000"/>
  </job>
  <job id="ID00085" namespace="CyberShake" name="PeakValCalcOkaya" version="1.0" runtime="0.90">
    <uses file="Seismogram_FFI_1_0_ID00084.grm" link="input" register="false" transfer="false" optional="false" type="data" size="24000"/>
    <uses file="PeakVals_FFI_1_0_ID00084.bsa" link="output" register="false" transfer="false" optional="false" type="data" size="216"/>
  </job>
  <job id="ID00086" namespace="CyberShake" name="SeismogramSynthesis" version="1.0" runtime="25.53">
    <uses file="FFI_1_0_txt.variation-s04993-h06270" link="input" register="true" transfer="true" optional="false" type="data" size="3149385"/>
    <uses file="FFI_1_0_subfx.sgt" link="input" register="false" transfer="false" optional="false" type="data" size="154694970"/>
    <uses file="FFI_1_0_subfy.sgt" link="input" register="false" transfer="false" optional="false" type="data" size="154694970"/>
    <uses file="Seismogram_FFI_1_0_ID00086.grm" link="output" register="false" transfer="false" optional="false" type="data" size="24000"/>
  </job>
  <job id="ID00087" namespace="CyberShake" name="PeakValCalcOkaya" version="1.0" runtime="0.66">
    <uses file="Seismogram_FFI_1_0_ID00086.grm" link="input" register="false" transfer="false" optional="false" type="data" size="24000"/>
    <uses file="PeakVals_FFI_1_0_ID00086.bsa" link="output" register="false" transfer="false" optional="false" type="data" size="216"/>
  </job>
  <job id="ID00088" namespace="CyberShake" name="SeismogramSynthesis" version="1.0" runtime="51.21">
    <uses file="FFI_1_0_txt.variation-s05040-h02883" link="input" register="true" transfer="true" optional="false" type="data" size="3362922"/>
    <uses file="FFI_1_0_subfx.sgt" link="input" register="false" transfer="false" optional="false" type="data" size="148998454"/>
    <uses file="FFI_1_0_subfy.sgt" link="input" register="false" transfer="false" optional="false" type="data" size="148998454"/>
    <uses file="Seismogram_FFI_1_0_ID00088.grm" link="output" register="false" transfer="false" optional="false" type="data" size="24000"/>
  </job>
  <job id="ID00089" namespace="CyberShake" name="PeakValCalcOkaya" version="1.0" runtime="1.43">
    <uses file="Seismogram_FFI_1_0_ID00088.grm" link="input" register="false" transfer="false" optional="false" type="data" size="24000"/>
    <uses file="PeakVals_FFI_1_0_ID00088.bsa" link="output" register="false" transfer="false" optional="false" type="data" size="216"/>
  </job>
  <job id="ID00090" namespace="CyberShake" name="SeismogramSynthesis" version="1.0" runtime="60.16">
    <uses file="FFI_1_0_txt.variation-s08063-h00129" link="input" register="true" transfer="true" optional="false" type="data" size="3851091"/>
    <uses file="FFI_1_0_subfx.sgt" link="input" register="false" transfer="false" optional="false" type="data" size="283592476"/>
    <uses file="FFI_1_0_subfy.sgt" link="input" register="false" transfer="false" optional="false" type="data" size="283592476"/>
    <uses file="Seismogram_FFI_1_0_ID00090.grm" link="output" register="false" transfer="false" optional="false" type="data" size="24000"/>
  </job>
  <job id="ID00091" namespace="CyberShake" name="PeakValCalcOkaya" version="1.0" runtime="0.58">
    <uses file="Seismogram_FFI_1_0_ID00090.grm" link="input" register="false" transfer="false" optional="false" type="data" size="24000"/>
    <uses file="PeakVals_FFI_1_0_ID00090.bsa" link="output" register="false" transfer="false" optional="false" type="data" size="216"/>
  </job>
  <job id="ID00092" namespace="CyberShake" name="SeismogramSynthesis" version="1.0" runtime="29.99">
    <uses file="FFI_1_0_txt.variation-s03760-h06908" link="input" register="true" transfer="true" optional="false" type="data" size="2140530"/>
    <uses file="FFI_1_0_subfx.sgt" link="input" register="false" transfer="false" optional="false" type="data" size="340903891"/>
    <uses file="FFI_1_0_subfy.sgt" link="input" register="false" transfer="false" optional="false" type="data" size="340903891"/>
    <uses file="Seismogram_FFI_1_0_ID00092.grm" link="output" register="false" transfer="false" optional="false" type="data" size="24000"/>
  </job>
  <job id="ID00093" namespace="CyberShake" name="PeakValCalcOkaya" version="1.0" runtime="1.61">
    <uses file="Seismogram_FFI_1_0_ID00092.grm" link="input" register="false" transfer="false" optional="false" type="data" size="24000"/>
    <uses file="PeakVals_FFI_1_0_ID00092.bsa" link="output" register="false" transfer="false" optional="false" type="data" size="216"/>
  </job>
  <job id="ID00094" namespace="CyberShake" name="SeismogramSynthesis" version="1.0" runtime="59.95">
    <uses file="FFI_1_0_txt.variation-s03911-h02566" link="input" register="true" transfer="true" optional="false" type="data" size="2265732"/>
    <uses file="FFI_1_0_subfx.sgt" link="input" register="false" transfer="false" optional="false" type="data" size="279421405"/>
    <uses file="FFI_1_0_subfy.sgt" link="input" register="false" transfer="false" optional="false" type="data" size="279421405"/>
    <uses file="Seismogram_FFI_1_0_ID00094.grm" link="output" register="false" transfer="false" optional="false" type="data" size="24000"/>
  </job>
  <job id="ID00095" namespace="CyberShake" name="PeakValCalcOkaya" version="1.0" runtime="1.08">
    <uses file="Seismogram_FFI_1_0_ID00094.grm" link="input" register="false" transfer="false" optional="false" type="data" size="24000"/>
    <uses file="PeakVals_FFI_1_0_ID00094.bsa" link="output" register="false" transfer="false" optional="false" type="data" size="216"/>
  </job>
  <job id="ID00096" namespace="CyberShake" name="SeismogramSynthesis" version="1.0" runtime="44.59">
    <uses file="FFI_1_0_txt.variation-s06743-h00984" link="input" register="true" transfer="true" optional="false" type="data" size="4929142"/>
    <uses file="FFI_1_0_subfx.sgt" link="input" register="false" transfer="false" optional="false" type="data" size="197406880"/>
    <uses file="FFI_1_0_subfy.sgt" link="input" register="false" transfer="false" optional="false" type="data" size="197406880"/>
    <uses file="Seismogram_FFI_1_0_ID00096.grm" link="output" register="false" transfer="false" optional="false" type="data" size="24000"/>
  </job>
  <job id="ID00097" namespace="CyberShake" name="PeakValCalcOkaya" version="1.0" runtime="1.32">
    <uses file="Seismogram_FFI_1_0_ID00096.grm" link="input" register="false" transfer="false" optional="false" type="data" size="24000"/>
    <uses file="PeakVals_FFI_1_0_ID00096.bsa" link="output" register="false" transfer="false" optional="false" type="data" size="216"/>
  </job>
  <job id="ID00098" namespace="CyberShake" name="SeismogramSynthesis" version="1.0" runtime="54.07">
    <uses file="FFI_1_0_txt.variation-s01617-h01951" link="input" register="true" transfer="true" optional="false" type="data" size="2825284"/>
    <uses file="FFI_1_0_subfx.sgt" link="input" register="false" transfer="false" optional="false" type="data" size="285256608"/>
    <uses file="FFI_1_0_subfy.sgt" link="input" register="false" transfer="false" optional="false" type="data" size="285256608"/>
    <uses file="Seismogram_FFI_1_0_ID00098.grm" link="output" register="false" transfer="false" optional="false" type="data" size="24000"/>
  </job>
  <job id="ID00099" namespace="CyberShake" name="PeakValCalcOkaya" version="1.0" runtime="0.77">
    <uses file="Seismogram_FFI_1_0_ID00098.grm" link="input" register="false" transfer="false" optional="false" type="data" size="24000"/>
    <uses file="PeakVals_FFI_1_0_ID00098.bsa" link="output" register="false" transfer="false" optional="false" type="data" size="216"/>
  </job>
<!-- part 3: list of control-flow dependencies (may be empty) -->
  <child ref="ID00000">
    <parent ref="ID00081"/>
    <parent ref="ID00006"/>
    <parent ref="ID00028"/>
    <parent ref="ID00004"/>
    <parent ref="ID00026"/>
    <parent ref="ID00048"/>
    <parent ref="ID00069"/>
    <parent ref="ID00008"/>
    <parent ref="ID00020"/>
    <parent ref="ID00042"/>
    <parent ref="ID00063"/>
    <parent ref="ID00085"/>
    <parent ref="ID00040"/>
    <parent ref="ID00061"/>
    <parent ref="ID00083"/>
    <parent ref="ID00024"/>
    <parent ref="ID00046"/>
    <parent ref="ID00067"/>
    <parent ref="ID00089"/>
    <parent ref="ID00022"/>
    <parent ref="ID00044"/>
    <parent ref="ID00065"/>
    <parent ref="ID00087"/>
    <parent ref="ID00071"/>
    <parent ref="ID00093"/>
    <parent ref="ID00091"/>
    <parent ref="ID00016"/>
    <parent ref="ID00038"/>
    <parent ref="ID00059"/>
    <parent ref="ID00014"/>
    <parent ref="ID00036"/>
    <parent ref="ID00018"/>
    <parent ref="ID00053"/>
    <parent ref="ID00075"/>
    <parent ref="ID00097"/>
    <parent ref="ID00030"/>
    <parent ref="ID00073"/>
    <parent ref="ID00095"/>
    <parent ref="ID00050"/>
    <parent ref="ID00057"/>
    <parent ref="ID00079"/>
    <parent ref="ID00012"/>
    <parent ref="ID00034"/>
    <parent ref="ID00055"/>
    <parent ref="ID00077"/>
    <parent ref="ID00099"/>
    <parent ref="ID00010"/>
    <parent ref="ID00032"/>
  </child>
  <child ref="ID00001">
    <parent ref="ID00060"/>
    <parent ref="ID00082"/>
    <parent ref="ID00080"/>
    <parent ref="ID00005"/>
    <parent ref="ID00027"/>
    <parent ref="ID00049"/>
    <parent ref="ID00003"/>
    <parent ref="ID00025"/>
    <parent ref="ID00047"/>
    <parent ref="ID00009"/>
    <parent ref="ID00007"/>
    <parent ref="ID00029"/>
    <parent ref="ID00064"/>
    <parent ref="ID00086"/>
    <parent ref="ID00041"/>
    <parent ref="ID00062"/>
    <parent ref="ID00084"/>
    <parent ref="ID00068"/>
    <parent ref="ID00023"/>
    <parent ref="ID00045"/>
    <parent ref="ID00066"/>
    <parent ref="ID00088"/>
    <parent ref="ID00021"/>
    <parent ref="ID00043"/>
    <parent ref="ID00070"/>
    <parent ref="ID00092"/>
    <parent ref="ID00090"/>
    <parent ref="ID00017"/>
    <parent ref="ID00039"/>
    <parent ref="ID00015"/>
    <parent ref="ID00037"/>
    <parent ref="ID00058"/>
    <parent ref="ID00019"/>
    <parent ref="ID00031"/>
    <parent ref="ID00052"/>
    <parent ref="ID00074"/>
    <parent ref="ID00096"/>
    <parent ref="ID00072"/>
    <parent ref="ID00094"/>
    <parent ref="ID00013"/>
    <parent ref="ID00035"/>
    <parent ref="ID00056"/>
    <parent ref="ID00078"/>
    <parent ref="ID00011"/>
    <parent ref="ID00033"/>
    <parent ref="ID00054"/>
    <parent ref="ID00076"/>
    <parent ref="ID00098"/>
  </child>
  <child ref="ID00003">
    <parent ref="ID00002"/>
  </child>
  <child ref="ID00004">
    <parent ref="ID00003"/>
  </child>
  <child ref="ID00005">
    <parent ref="ID00002"/>
  </child>
  <child ref="ID00006">
    <parent ref="ID00005"/>
  </child>
  <child ref="ID00007">
    <parent ref="ID00002"/>
  </child>
  <child ref="ID00008">
    <parent ref="ID00007"/>
  </child>
  <child ref="ID00009">
    <parent ref="ID00002"/>
  </child>
  <child ref="ID00010">
    <parent ref="ID00009"/>
  </child>
  <child ref="ID00011">
    <parent ref="ID00002"/>
  </child>
  <child ref="ID00012">
    <parent ref="ID00011"/>
  </child>
  <child ref="ID00013">
    <parent ref="ID00002"/>
  </child>
  <child ref="ID00014">
    <parent ref="ID00013"/>
  </child>
  <child ref="ID00015">
    <parent ref="ID00002"/>
  </child>
  <child ref="ID00016">
    <parent ref="ID00015"/>
  </child>
  <child ref="ID00017">
    <parent ref="ID00002"/>
  </child>
  <child ref="ID00018">
    <parent ref="ID00017"/>
  </child>
  <child ref="ID00019">
    <parent ref="ID00002"/>
  </child>
  <child ref="ID00020">
    <parent ref="ID00019"/>
  </child>
  <child ref="ID00021">
    <parent ref="ID00002"/>
  </child>
  <child ref="ID00022">
    <parent ref="ID00021"/>
  </child>
  <child ref="ID00023">
    <parent ref="ID00002"/>
  </child>
  <child ref="ID00024">
    <parent ref="ID00023"/>
  </child>
  <child ref="ID00025">
    <parent ref="ID00002"/>
  </child>
  <child ref="ID00026">
    <parent ref="ID00025"/>
  </child>
  <child ref="ID00027">
    <parent ref="ID00002"/>
  </child>
  <child ref="ID00028">
    <parent ref="ID00027"/>
  </child>
  <child ref="ID00029">
    <parent ref="ID00002"/>
  </child>
  <child ref="ID00030">
    <parent ref="ID00029"/>
  </child>
  <child ref="ID00031">
    <parent ref="ID00002"/>
  </child>
  <child ref="ID00032">
    <parent ref="ID00031"/>
  </child>
  <child ref="ID00033">
    <parent ref="ID00002"/>
  </child>
  <child ref="ID00034">
    <parent ref="ID00033"/>
  </child>
  <child ref="ID00035">
    <parent ref="ID00002"/>
  </child>
  <child ref="ID00036">
    <parent ref="ID00035"/>
  </child>
  <child ref="ID00037">
    <parent ref="ID00002"/>
  </child>
  <child ref="ID00038">
    <parent ref="ID00037"/>
  </child>
  <child ref="ID00039">
    <parent ref="ID00002"/>
  </child>
  <child ref="ID00040">
    <parent ref="ID00039"/>
  </child>
  <child ref="ID00041">
    <parent ref="ID00002"/>
  </child>
  <child ref="ID00042">
    <parent ref="ID00041"/>
  </child>
  <child ref="ID00043">
    <parent ref="ID00002"/>
  </child>
  <child ref="ID00044">
    <parent ref="ID00043"/>
  </child>
  <child ref="ID00045">
    <parent ref="ID00002"/>
  </child>
  <child ref="ID00046">
    <parent ref="ID00045"/>
  </child>
  <child ref="ID00047">
    <parent ref="ID00002"/>
  </child>
  <child ref="ID00048">
    <parent ref="ID00047"/>
  </child>
  <child ref="ID00049">
    <parent ref="ID00002"/>
  </child>
  <child ref="ID00050">
    <parent ref="ID00049"/>
  </child>
  <child ref="ID00052">
    <parent ref="ID00051"/>
  </child>
  <child ref="ID00053">
    <parent ref="ID00052"/>
  </child>
  <child ref="ID00054">
    <parent ref="ID00051"/>
  </child>
  <child ref="ID00055">
    <parent ref="ID00054"/>
  </child>
  <child ref="ID00056">
    <parent ref="ID00051"/>
  </child>
  <child ref="ID00057">
    <parent ref="ID00056"/>
  </child>
  <child ref="ID00058">
    <parent ref="ID00051"/>
  </child>
  <child ref="ID00059">
    <parent ref="ID00058"/>
  </child>
  <child ref="ID00060">
    <parent ref="ID00051"/>
  </child>
  <child ref="ID00061">
    <parent ref="ID00060"/>
  </child>
  <child ref="ID00062">
    <parent ref="ID00051"/>
  </child>
  <child ref="ID00063">
    <parent ref="ID00062"/>
  </child>
  <child ref="ID00064">
    <parent ref="ID00051"/>
  </child>
  <child ref="ID00065">
    <parent ref="ID00064"/>
  </child>
  <child ref="ID00066">
    <parent ref="ID00051"/>
  </child>
  <child ref="ID00067">
    <parent ref="ID00066"/>
  </child>
  <child ref="ID00068">
    <parent ref="ID00051"/>
  </child>
  <child ref="ID00069">
    <parent ref="ID00068"/>
  </child>
  <child ref="ID00070">
    <parent ref="ID00051"/>
  </child>
  <child ref="ID00071">
    <parent ref="ID00070"/>
  </child>
  <child ref="ID00072">
    <parent ref="ID00051"/>
  </child>
  <child ref="ID00073">
    <parent ref="ID00072"/>
  </child>
  <child ref="ID00074">
    <parent ref="ID00051"/>
  </child>
  <child ref="ID00075">
    <parent ref="ID00074"/>
  </child>
  <child ref="ID00076">
    <parent ref="ID00051"/>
  </child>
  <child ref="ID00077">
    <parent ref="ID00076"/>
  </child>
  <child ref="ID00078">
    <parent ref="ID00051"/>
  </child>
  <child ref="ID00079">
    <parent ref="ID00078"/>
  </child>
  <child ref="ID00080">
    <parent ref="ID00051"/>
  </child>
  <child ref="ID00081">
    <parent ref="ID00080"/>
  </child>
  <child ref="ID00082">
    <parent ref="ID00051"/>
  </child>
  <child ref="ID00083">
    <parent ref="ID00082"/>
  </child>
  <child ref="ID00084">
    <parent ref="ID00051"/>
  </child>
  <child ref="ID00085">
    <parent ref="ID00084"/>
  </child>
  <child ref="ID00086">
    <parent ref="ID00051"/>
  </child>
  <child ref="ID00087">
    <parent ref="ID00086"/>
  </child>
  <child ref="ID00088">
    <parent ref="ID00051"/>
  </child>
  <child ref="ID00089">
    <parent ref="ID00088"/>
  </child>
  <child ref="ID00090">
    <parent ref="ID00051"/>
  </child>
  <child ref="ID00091">
    <parent ref="ID00090"/>
  </child>
  <child ref="ID00092">
    <parent ref="ID00051"/>
  </child>
  <child ref="ID00093">
    <parent ref="ID00092"/>
  </child>
  <child ref="ID00094">
    <parent ref="ID00051"/>
  </child>
  <child ref="ID00095">
    <parent ref="ID00094"/>
  </child>
  <child ref="ID00096">
    <parent ref="ID00051"/>
  </child>
  <child ref="ID00097">
    <parent ref="ID00096"/>
  </child>
  <child ref="ID00098">
    <parent ref="ID00051"/>
  </child>
  <child ref="ID00099">
    <parent ref="ID00098"/>
  </child>
</adag>
