<?xml version="1.0" encoding="UTF-8"?>
<!-- generated: 2025-06-03T15:50:09+08:00 -->
<!-- generated by: qiujie [??] -->
<adag xmlns="http://pegasus.isi.edu/schema/DAX" xmlns:xsi="http://www.w3.org/2001/XMLSchema-instance" xsi:schemaLocation="http://pegasus.isi.edu/schema/DAX http://pegasus.isi.edu/schema/dax-2.1.xsd" version="2.1" count="1" index="0" name="test" jobCount="50" fileCount="0" childCount="48">
<!-- part 1: list of all referenced files (may be empty) -->
<!-- part 2: definition of all jobs (at least one) -->
  <job id="ID00000" namespace="CyberShake" name="ZipPSA" version="1.0" runtime="0.18">
    <uses file="PeakVals_FFI_0_1_ID00003.bsa" link="input" register="false" transfer="false" optional="false" type="data" size="216"/>
    <uses file="PeakVals_FFI_0_1_ID00005.bsa" link="input" register="false" transfer="false" optional="false" type="data" size="216"/>
    <uses file="PeakVals_FFI_0_1_ID00007.bsa" link="input" register="false" transfer="false" optional="false" type="data" size="216"/>
    <uses file="PeakVals_FFI_0_1_ID00009.bsa" link="input" register="false" transfer="false" optional="false" type="data" size="216"/>
    <uses file="PeakVals_FFI_0_1_ID00011.bsa" link="input" register="false" transfer="false" optional="false" type="data" size="216"/>
    <uses file="PeakVals_FFI_0_1_ID00013.bsa" link="input" register="false" transfer="false" optional="false" type="data" size="216"/>
    <uses file="PeakVals_FFI_0_1_ID00015.bsa" link="input" register="false" transfer="false" optional="false" type="data" size="216"/>
    <uses file="PeakVals_FFI_0_1_ID00017.bsa" link="input" register="false" transfer="false" optional="false" type="data" size="216"/>
    <uses file="PeakVals_FFI_0_1_ID00019.bsa" link="input" register="false" transfer="false" optional="false" type="data" size="216"/>
    <uses file="PeakVals_FFI_0_1_ID00021.bsa" link="input" register="false" transfer="false" optional="false" type="data" size="216"/>
    <uses file="PeakVals_FFI_0_2_ID00024.bsa" link="input" register="false" transfer="false" optional="false" type="data" size="216"/>
    <uses file="PeakVals_FFI_0_2_ID00026.bsa" link="input" register="false" transfer="false" optional="false" type="data" size="216"/>
    <uses file="PeakVals_FFI_0_2_ID00028.bsa" link="input" register="false" transfer="false" optional="false" type="data" size="216"/>
    <uses file="PeakVals_FFI_0_2_ID00030.bsa" link="input" register="false" transfer="false" optional="false" type="data" size="216"/>
    <uses file="PeakVals_FFI_0_2_ID00032.bsa" link="input" register="false" transfer="false" optional="false" type="data" size="216"/>
    <uses file="PeakVals_FFI_0_2_ID00034.bsa" link="input" register="false" transfer="false" optional="false" type="data" size="216"/>
    <uses file="PeakVals_FFI_0_2_ID00036.bsa" link="input" register="false" transfer="false" optional="false" type="data" size="216"/>
    <uses file="PeakVals_FFI_0_2_ID00038.bsa" link="input" register="false" transfer="false" optional="false" type="data" size="216"/>
    <uses file="PeakVals_FFI_0_2_ID00040.bsa" link="input" register="false" transfer="false" optional="false" type="data" size="216"/>
    <uses file="PeakVals_FFI_0_2_ID00042.bsa" link="input" register="false" transfer="false" optional="false" type="data" size="216"/>
    <uses file="PeakVals_FFI_0_2_ID00044.bsa" link="input" register="false" transfer="false" optional="false" type="data" size="216"/>
    <uses file="PeakVals_FFI_0_2_ID00046.bsa" link="input" register="false" transfer="false" optional="false" type="data" size="216"/>
    <uses file="PeakVals_FFI_0_2_ID00048.bsa" link="input" register="false" transfer="false" optional="false" type="data" size="216"/>
    <uses file="Cybershake_PSA.zip" link="output" register="true" transfer="true" optional="false" type="data" size="491"/>
  </job>
  <job id="ID00001" namespace="CyberShake" name="ZipSeis" version="1.0" runtime="0.28">
    <uses file="Seismogram_FFI_0_1_ID00003.grm" link="input" register="false" transfer="false" optional="false" type="data" size="24000"/>
    <uses file="Seismogram_FFI_0_1_ID00005.grm" link="input" register="false" transfer="false" optional="false" type="data" size="24000"/>
    <uses file="Seismogram_FFI_0_1_ID00007.grm" link="input" register="false" transfer="false" optional="false" type="data" size="24000"/>
    <uses file="Seismogram_FFI_0_1_ID00009.grm" link="input" register="false" transfer="false" optional="false" type="data" size="24000"/>
    <uses file="Seismogram_FFI_0_1_ID00011.grm" link="input" register="false" transfer="false" optional="false" type="data" size="24000"/>
    <uses file="Seismogram_FFI_0_1_ID00013.grm" link="input" register="false" transfer="false" optional="false" type="data" size="24000"/>
    <uses file="Seismogram_FFI_0_1_ID00015.grm" link="input" register="false" transfer="false" optional="false" type="data" size="24000"/>
    <uses file="Seismogram_FFI_0_1_ID00017.grm" link="input" register="false" transfer="false" optional="false" type="data" size="24000"/>
    <uses file="Seismogram_FFI_0_1_ID00019.grm" link="input" register="false" transfer="false" optional="false" type="data" size="24000"/>
    <uses file="Seismogram_FFI_0_1_ID00021.grm" link="input" register="false" transfer="false" optional="false" type="data" size="24000"/>
    <uses file="Seismogram_FFI_0_2_ID00024.grm" link="input" register="false" transfer="false" optional="false" type="data" size="24000"/>
    <uses file="Seismogram_FFI_0_2_ID00026.grm" link="input" register="false" transfer="false" optional="false" type="data" size="24000"/>
    <uses file="Seismogram_FFI_0_2_ID00028.grm" link="input" register="false" transfer="false" optional="false" type="data" size="24000"/>
    <uses file="Seismogram_FFI_0_2_ID00030.grm" link="input" register="false" transfer="false" optional="false" type="data" size="24000"/>
    <uses file="Seismogram_FFI_0_2_ID00032.grm" link="input" register="false" transfer="false" optional="false" type="data" size="24000"/>
    <uses file="Seismogram_FFI_0_2_ID00034.grm" link="input" register="false" transfer="false" optional="false" type="data" size="24000"/>
    <uses file="Seismogram_FFI_0_2_ID00036.grm" link="input" register="false" transfer="false" optional="false" type="data" size="24000"/>
    <uses file="Seismogram_FFI_0_2_ID00038.grm" link="input" register="false" transfer="false" optional="false" type="data" size="24000"/>
    <uses file="Seismogram_FFI_0_2_ID00040.grm" link="input" register="false" transfer="false" optional="false" type="data" size="24000"/>
    <uses file="Seismogram_FFI_0_2_ID00042.grm" link="input" register="false" transfer="false" optional="false" type="data" size="24000"/>
    <uses file="Seismogram_FFI_0_2_ID00044.grm" link="input" register="false" transfer="false" optional="false" type="data" size="24000"/>
    <uses file="Seismogram_FFI_0_2_ID00046.grm" link="input" register="false" transfer="false" optional="false" type="data" size="24000"/>
    <uses file="Seismogram_FFI_0_2_ID00048.grm" link="input" register="false" transfer="false" optional="false" type="data" size="24000"/>
    <uses file="Cybershake_Seismograms.zip" link="output" register="true" transfer="true" optional="false" type="data" size="63184"/>
  </job>
  <job id="ID00002" namespace="CyberShake" name="ExtractSGT" version="1.0" runtime="92.12">
    <uses file="FFI_0_1_fx.sgt" link="input" register="true" transfer="true" optional="false" type="data" size="20293617596"/>
    <uses file="FFI_0_1_fy.sgt" link="input" register="true" transfer="true" optional="false" type="data" size="20293617596"/>
    <uses file="FFI_0_1_subfx.sgt" link="output" register="false" transfer="false" optional="false" type="data" size="345084923"/>
    <uses file="FFI_0_1_subfy.sgt" link="output" register="false" transfer="false" optional="false" type="data" size="345084923"/>
    <uses file="FFI_0_1_txt.variation-s04162-h06717" link="input" register="true" transfer="true" optional="false" type="data" size="2096454"/>
  </job>
  <job id="ID00003" namespace="CyberShake" name="SeismogramSynthesis" version="1.0" runtime="57.07">
    <uses file="FFI_0_1_txt.variation-s02334-h03639" link="input" register="true" transfer="true" optional="false" type="data" size="4315910"/>
    <uses file="FFI_0_1_subfx.sgt" link="input" register="false" transfer="false" optional="false" type="data" size="345084923"/>
    <uses file="FFI_0_1_subfy.sgt" link="input" register="false" transfer="false" optional="false" type="data" size="345084923"/>
    <uses file="Seismogram_FFI_0_1_ID00003.grm" link="output" register="false" transfer="false" optional="false" type="data" size="24000"/>
  </job>
  <job id="ID00004" namespace="CyberShake" name="PeakValCalcOkaya" version="1.0" runtime="0.87">
    <uses file="Seismogram_FFI_0_1_ID00003.grm" link="input" register="false" transfer="false" optional="false" type="data" size="24000"/>
    <uses file="PeakVals_FFI_0_1_ID00003.bsa" link="output" register="false" transfer="false" optional="false" type="data" size="216"/>
  </job>
  <job id="ID00005" namespace="CyberShake" name="SeismogramSynthesis" version="1.0" runtime="52.44">
    <uses file="FFI_0_1_txt.variation-s04744-h08889" link="input" register="true" transfer="true" optional="false" type="data" size="2767401"/>
    <uses file="FFI_0_1_subfx.sgt" link="input" register="false" transfer="false" optional="false" type="data" size="342389060"/>
    <uses file="FFI_0_1_subfy.sgt" link="input" register="false" transfer="false" optional="false" type="data" size="342389060"/>
    <uses file="Seismogram_FFI_0_1_ID00005.grm" link="output" register="false" transfer="false" optional="false" type="data" size="24000"/>
  </job>
  <job id="ID00006" namespace="CyberShake" name="PeakValCalcOkaya" version="1.0" runtime="0.73">
    <uses file="Seismogram_FFI_0_1_ID00005.grm" link="input" register="false" transfer="false" optional="false" type="data" size="24000"/>
    <uses file="PeakVals_FFI_0_1_ID00005.bsa" link="output" register="false" transfer="false" optional="false" type="data" size="216"/>
  </job>
  <job id="ID00007" namespace="CyberShake" name="SeismogramSynthesis" version="1.0" runtime="42.59">
    <uses file="FFI_0_1_txt.variation-s09030-h07461" link="input" register="true" transfer="true" optional="false" type="data" size="3989966"/>
    <uses file="FFI_0_1_subfx.sgt" link="input" register="false" transfer="false" optional="false" type="data" size="154352452"/>
    <uses file="FFI_0_1_subfy.sgt" link="input" register="false" transfer="false" optional="false" type="data" size="154352452"/>
    <uses file="Seismogram_FFI_0_1_ID00007.grm" link="output" register="false" transfer="false" optional="false" type="data" size="24000"/>
  </job>
  <job id="ID00008" namespace="CyberShake" name="PeakValCalcOkaya" version="1.0" runtime="1.20">
    <uses file="Seismogram_FFI_0_1_ID00007.grm" link="input" register="false" transfer="false" optional="false" type="data" size="24000"/>
    <uses file="PeakVals_FFI_0_1_ID00007.bsa" link="output" register="false" transfer="false" optional="false" type="data" size="216"/>
  </job>
  <job id="ID00009" namespace="CyberShake" name="SeismogramSynthesis" version="1.0" runtime="56.62">
    <uses file="FFI_0_1_txt.variation-s07911-h06384" link="input" register="true" transfer="true" optional="false" type="data" size="2579245"/>
    <uses file="FFI_0_1_subfx.sgt" link="input" register="false" transfer="false" optional="false" type="data" size="298371568"/>
    <uses file="FFI_0_1_subfy.sgt" link="input" register="false" transfer="false" optional="false" type="data" size="298371568"/>
    <uses file="Seismogram_FFI_0_1_ID00009.grm" link="output" register="false" transfer="false" optional="false" type="data" size="24000"/>
  </job>
  <job id="ID00010" namespace="CyberShake" name="PeakValCalcOkaya" version="1.0" runtime="1.43">
    <uses file="Seismogram_FFI_0_1_ID00009.grm" link="input" register="false" transfer="false" optional="false" type="data" size="24000"/>
    <uses file="PeakVals_FFI_0_1_ID00009.bsa" link="output" register="false" transfer="false" optional="false" type="data" size="216"/>
  </job>
  <job id="ID00011" namespace="CyberShake" name="SeismogramSynthesis" version="1.0" runtime="30.97">
    <uses file="FFI_0_1_txt.variation-s01834-h01184" link="input" register="true" transfer="true" optional="false" type="data" size="2182967"/>
    <uses file="FFI_0_1_subfx.sgt" link="input" register="false" transfer="false" optional="false" type="data" size="235327721"/>
    <uses file="FFI_0_1_subfy.sgt" link="input" register="false" transfer="false" optional="false" type="data" size="235327721"/>
    <uses file="Seismogram_FFI_0_1_ID00011.grm" link="output" register="false" transfer="false" optional="false" type="data" size="24000"/>
  </job>
  <job id="ID00012" namespace="CyberShake" name="PeakValCalcOkaya" version="1.0" runtime="1.21">
    <uses file="Seismogram_FFI_0_1_ID00011.grm" link="input" register="false" transfer="false" optional="false" type="data" size="24000"/>
    <uses file="PeakVals_FFI_0_1_ID00011.bsa" link="output" register="false" transfer="false" optional="false" type="data" size="216"/>
  </job>
  <job id="ID00013" namespace="CyberShake" name="SeismogramSynthesis" version="1.0" runtime="42.35">
    <uses file="FFI_0_1_txt.variation-s08364-h06960" link="input" register="true" transfer="true" optional="false" type="data" size="4772403"/>
    <uses file="FFI_0_1_subfx.sgt" link="input" register="false" transfer="false" optional="false" type="data" size="258193070"/>
    <uses file="FFI_0_1_subfy.sgt" link="input" register="false" transfer="false" optional="false" type="data" size="258193070"/>
    <uses file="Seismogram_FFI_0_1_ID00013.grm" link="output" register="false" transfer="false" optional="false" type="data" size="24000"/>
  </job>
  <job id="ID00014" namespace="CyberShake" name="PeakValCalcOkaya" version="1.0" runtime="1.54">
    <uses file="Seismogram_FFI_0_1_ID00013.grm" link="input" register="false" transfer="false" optional="false" type="data" size="24000"/>
    <uses file="PeakVals_FFI_0_1_ID00013.bsa" link="output" register="false" transfer="false" optional="false" type="data" size="216"/>
  </job>
  <job id="ID00015" namespace="CyberShake" name="SeismogramSynthesis" version="1.0" runtime="57.08">
    <uses file="FFI_0_1_txt.variation-s09887-h02649" link="input" register="true" transfer="true" optional="false" type="data" size="2235887"/>
    <uses file="FFI_0_1_subfx.sgt" link="input" register="false" transfer="false" optional="false" type="data" size="293707490"/>
    <uses file="FFI_0_1_subfy.sgt" link="input" register="false" transfer="false" optional="false" type="data" size="293707490"/>
    <uses file="Seismogram_FFI_0_1_ID00015.grm" link="output" register="false" transfer="false" optional="false" type="data" size="24000"/>
  </job>
  <job id="ID00016" namespace="CyberShake" name="PeakValCalcOkaya" version="1.0" runtime="1.45">
    <uses file="Seismogram_FFI_0_1_ID00015.grm" link="input" register="false" transfer="false" optional="false" type="data" size="24000"/>
    <uses file="PeakVals_FFI_0_1_ID00015.bsa" link="output" register="false" transfer="false" optional="false" type="data" size="216"/>
  </job>
  <job id="ID00017" namespace="CyberShake" name="SeismogramSynthesis" version="1.0" runtime="47.99">
    <uses file="FFI_0_1_txt.variation-s00070-h04872" link="input" register="true" transfer="true" optional="false" type="data" size="2121718"/>
    <uses file="FFI_0_1_subfx.sgt" link="input" register="false" transfer="false" optional="false" type="data" size="281313510"/>
    <uses file="FFI_0_1_subfy.sgt" link="input" register="false" transfer="false" optional="false" type="data" size="281313510"/>
    <uses file="Seismogram_FFI_0_1_ID00017.grm" link="output" register="false" transfer="false" optional="false" type="data" size="24000"/>
  </job>
  <job id="ID00018" namespace="CyberShake" name="PeakValCalcOkaya" version="1.0" runtime="1.57">
    <uses file="Seismogram_FFI_0_1_ID00017.grm" link="input" register="false" transfer="false" optional="false" type="data" size="24000"/>
    <uses file="PeakVals_FFI_0_1_ID00017.bsa" link="output" register="false" transfer="false" optional="false" type="data" size="216"/>
  </job>
  <job id="ID00019" namespace="CyberShake" name="SeismogramSynthesis" version="1.0" runtime="25.82">
    <uses file="FFI_0_1_txt.variation-s03969-h01086" link="input" register="true" transfer="true" optional="false" type="data" size="4026227"/>
    <uses file="FFI_0_1_subfx.sgt" link="input" register="false" transfer="false" optional="false" type="data" size="338870050"/>
    <uses file="FFI_0_1_subfy.sgt" link="input" register="false" transfer="false" optional="false" type="data" size="338870050"/>
    <uses file="Seismogram_FFI_0_1_ID00019.grm" link="output" register="false" transfer="false" optional="false" type="data" size="24000"/>
  </job>
  <job id="ID00020" namespace="CyberShake" name="PeakValCalcOkaya" version="1.0" runtime="0.78">
    <uses file="Seismogram_FFI_0_1_ID00019.grm" link="input" register="false" transfer="false" optional="false" type="data" size="24000"/>
    <uses file="PeakVals_FFI_0_1_ID00019.bsa" link="output" register="false" transfer="false" optional="false" type="data" size="216"/>
  </job>
  <job id="ID00021" namespace="CyberShake" name="SeismogramSynthesis" version="1.0" runtime="44.82">
    <uses file="FFI_0_1_txt.variation-s04162-h06717" link="input" register="true" transfer="true" optional="false" type="data" size="2096454"/>
    <uses file="FFI_0_1_subfx.sgt" link="input" register="false" transfer="false" optional="false" type="data" size="251839065"/>
    <uses file="FFI_0_1_subfy.sgt" link="input" register="false" transfer="false" optional="false" type="data" size="251839065"/>
    <uses file="Seismogram_FFI_0_1_ID00021.grm" link="output" register="false" transfer="false" optional="false" type="data" size="24000"/>
  </job>
  <job id="ID00022" namespace="CyberShake" name="PeakValCalcOkaya" version="1.0" runtime="0.61">
    <uses file="Seismogram_FFI_0_1_ID00021.grm" link="input" register="false" transfer="false" optional="false" type="data" size="24000"/>
    <uses file="PeakVals_FFI_0_1_ID00021.bsa" link="output" register="false" transfer="false" optional="false" type="data" size="216"/>
  </job>
  <job id="ID00023" namespace="CyberShake" name="ExtractSGT" version="1.0" runtime="202.46">
    <uses file="FFI_0_2_fx.sgt" link="input" register="true" transfer="true" optional="false" type="data" size="20212555044"/>
    <uses file="FFI_0_2_fy.sgt" link="input" register="true" transfer="true" optional="false" type="data" size="20212555044"/>
    <uses file="FFI_0_2_subfx.sgt" link="output" register="false" transfer="false" optional="false" type="data" size="306905849"/>
    <uses file="FFI_0_2_subfy.sgt" link="output" register="false" transfer="false" optional="false" type="data" size="306905849"/>
    <uses file="FFI_0_2_txt.variation-s02876-h04258" link="input" register="true" transfer="true" optional="false" type="data" size="4901632"/>
  </job>
  <job id="ID00024" namespace="CyberShake" name="SeismogramSynthesis" version="1.0" runtime="53.92">
    <uses file="FFI_0_2_txt.variation-s00551-h02479" link="input" register="true" transfer="true" optional="false" type="data" size="2565226"/>
    <uses file="FFI_0_2_subfx.sgt" link="input" register="false" transfer="false" optional="false" type="data" size="306905849"/>
    <uses file="FFI_0_2_subfy.sgt" link="input" register="false" transfer="false" optional="false" type="data" size="306905849"/>
    <uses file="Seismogram_FFI_0_2_ID00024.grm" link="output" register="false" transfer="false" optional="false" type="data" size="24000"/>
  </job>
  <job id="ID00025" namespace="CyberShake" name="PeakValCalcOkaya" version="1.0" runtime="0.78">
    <uses file="Seismogram_FFI_0_2_ID00024.grm" link="input" register="false" transfer="false" optional="false" type="data" size="24000"/>
    <uses file="PeakVals_FFI_0_2_ID00024.bsa" link="output" register="false" transfer="false" optional="false" type="data" size="216"/>
  </job>
  <job id="ID00026" namespace="CyberShake" name="SeismogramSynthesis" version="1.0" runtime="22.05">
    <uses file="FFI_0_2_txt.variation-s01144-h02124" link="input" register="true" transfer="true" optional="false" type="data" size="3503988"/>
    <uses file="FFI_0_2_subfx.sgt" link="input" register="false" transfer="false" optional="false" type="data" size="180534581"/>
    <uses file="FFI_0_2_subfy.sgt" link="input" register="false" transfer="false" optional="false" type="data" size="180534581"/>
    <uses file="Seismogram_FFI_0_2_ID00026.grm" link="output" register="false" transfer="false" optional="false" type="data" size="24000"/>
  </job>
  <job id="ID00027" namespace="CyberShake" name="PeakValCalcOkaya" version="1.0" runtime="0.81">
    <uses file="Seismogram_FFI_0_2_ID00026.grm" link="input" register="false" transfer="false" optional="false" type="data" size="24000"/>
    <uses file="PeakVals_FFI_0_2_ID00026.bsa" link="output" register="false" transfer="false" optional="false" type="data" size="216"/>
  </job>
  <job id="ID00028" namespace="CyberShake" name="SeismogramSynthesis" version="1.0" runtime="41.34">
    <uses file="FFI_0_2_txt.variation-s00181-h04560" link="input" register="true" transfer="true" optional="false" type="data" size="4892479"/>
    <uses file="FFI_0_2_subfx.sgt" link="input" register="false" transfer="false" optional="false" type="data" size="341213835"/>
    <uses file="FFI_0_2_subfy.sgt" link="input" register="false" transfer="false" optional="false" type="data" size="341213835"/>
    <uses file="Seismogram_FFI_0_2_ID00028.grm" link="output" register="false" transfer="false" optional="false" type="data" size="24000"/>
  </job>
  <job id="ID00029" namespace="CyberShake" name="PeakValCalcOkaya" version="1.0" runtime="1.25">
    <uses file="Seismogram_FFI_0_2_ID00028.grm" link="input" register="false" transfer="false" optional="false" type="data" size="24000"/>
    <uses file="PeakVals_FFI_0_2_ID00028.bsa" link="output" register="false" transfer="false" optional="false" type="data" size="216"/>
  </job>
  <job id="ID00030" namespace="CyberShake" name="SeismogramSynthesis" version="1.0" runtime="39.11">
    <uses file="FFI_0_2_txt.variation-s02702-h06564" link="input" register="true" transfer="true" optional="false" type="data" size="2318690"/>
    <uses file="FFI_0_2_subfx.sgt" link="input" register="false" transfer="false" optional="false" type="data" size="333116064"/>
    <uses file="FFI_0_2_subfy.sgt" link="input" register="false" transfer="false" optional="false" type="data" size="333116064"/>
    <uses file="Seismogram_FFI_0_2_ID00030.grm" link="output" register="false" transfer="false" optional="false" type="data" size="24000"/>
  </job>
  <job id="ID00031" namespace="CyberShake" name="PeakValCalcOkaya" version="1.0" runtime="1.37">
    <uses file="Seismogram_FFI_0_2_ID00030.grm" link="input" register="false" transfer="false" optional="false" type="data" size="24000"/>
    <uses file="PeakVals_FFI_0_2_ID00030.bsa" link="output" register="false" transfer="false" optional="false" type="data" size="216"/>
  </job>
  <job id="ID00032" namespace="CyberShake" name="SeismogramSynthesis" version="1.0" runtime="21.91">
    <uses file="FFI_0_2_txt.variation-s00072-h02008" link="input" register="true" transfer="true" optional="false" type="data" size="5466341"/>
    <uses file="FFI_0_2_subfx.sgt" link="input" register="false" transfer="false" optional="false" type="data" size="263771597"/>
    <uses file="FFI_0_2_subfy.sgt" link="input" register="false" transfer="false" optional="false" type="data" size="263771597"/>
    <uses file="Seismogram_FFI_0_2_ID00032.grm" link="output" register="false" transfer="false" optional="false" type="data" size="24000"/>
  </job>
  <job id="ID00033" namespace="CyberShake" name="PeakValCalcOkaya" version="1.0" runtime="1.38">
    <uses file="Seismogram_FFI_0_2_ID00032.grm" link="input" register="false" transfer="false" optional="false" type="data" size="24000"/>
    <uses file="PeakVals_FFI_0_2_ID00032.bsa" link="output" register="false" transfer="false" optional="false" type="data" size="216"/>
  </job>
  <job id="ID00034" namespace="CyberShake" name="SeismogramSynthesis" version="1.0" runtime="64.75">
    <uses file="FFI_0_2_txt.variation-s06083-h00271" link="input" register="true" transfer="true" optional="false" type="data" size="2483400"/>
    <uses file="FFI_0_2_subfx.sgt" link="input" register="false" transfer="false" optional="false" type="data" size="283392667"/>
    <uses file="FFI_0_2_subfy.sgt" link="input" register="false" transfer="false" optional="false" type="data" size="283392667"/>
    <uses file="Seismogram_FFI_0_2_ID00034.grm" link="output" register="false" transfer="false" optional="false" type="data" size="24000"/>
  </job>
  <job id="ID00035" namespace="CyberShake" name="PeakValCalcOkaya" version="1.0" runtime="0.57">
    <uses file="Seismogram_FFI_0_2_ID00034.grm" link="input" register="false" transfer="false" optional="false" type="data" size="24000"/>
    <uses file="PeakVals_FFI_0_2_ID00034.bsa" link="output" register="false" transfer="false" optional="false" type="data" size="216"/>
  </job>
  <job id="ID00036" namespace="CyberShake" name="SeismogramSynthesis" version="1.0" runtime="35.36">
    <uses file="FFI_0_2_txt.variation-s00984-h03564" link="input" register="true" transfer="true" optional="false" type="data" size="4082228"/>
    <uses file="FFI_0_2_subfx.sgt" link="input" register="false" transfer="false" optional="false" type="data" size="287067215"/>
    <uses file="FFI_0_2_subfy.sgt" link="input" register="false" transfer="false" optional="false" type="data" size="287067215"/>
    <uses file="Seismogram_FFI_0_2_ID00036.grm" link="output" register="false" transfer="false" optional="false" type="data" size="24000"/>
  </job>
  <job id="ID00037" namespace="CyberShake" name="PeakValCalcOkaya" version="1.0" runtime="1.59">
    <uses file="Seismogram_FFI_0_2_ID00036.grm" link="input" register="false" transfer="false" optional="false" type="data" size="24000"/>
    <uses file="PeakVals_FFI_0_2_ID00036.bsa" link="output" register="false" transfer="false" optional="false" type="data" size="216"/>
  </job>
  <job id="ID00038" namespace="CyberShake" name="SeismogramSynthesis" version="1.0" runtime="28.16">
    <uses file="FFI_0_2_txt.variation-s07324-h01014" link="input" register="true" transfer="true" optional="false" type="data" size="4378533"/>
    <uses file="FFI_0_2_subfx.sgt" link="input" register="false" transfer="false" optional="false" type="data" size="294324052"/>
    <uses file="FFI_0_2_subfy.sgt" link="input" register="false" transfer="false" optional="false" type="data" size="294324052"/>
    <uses file="Seismogram_FFI_0_2_ID00038.grm" link="output" register="false" transfer="false" optional="false" type="data" size="24000"/>
  </job>
  <job id="ID00039" namespace="CyberShake" name="PeakValCalcOkaya" version="1.0" runtime="1.38">
    <uses file="Seismogram_FFI_0_2_ID00038.grm" link="input" register="false" transfer="false" optional="false" type="data" size="24000"/>
    <uses file="PeakVals_FFI_0_2_ID00038.bsa" link="output" register="false" transfer="false" optional="false" type="data" size="216"/>
  </job>
  <job id="ID00040" namespace="CyberShake" name="SeismogramSynthesis" version="1.0" runtime="50.71">
    <uses file="FFI_0_2_txt.variation-s05459-h04962" link="input" register="true" transfer="true" optional="false" type="data" size="5244554"/>
    <uses file="FFI_0_2_subfx.sgt" link="input" register="false" transfer="false" optional="false" type="data" size="220179627"/>
    <uses file="FFI_0_2_subfy.sgt" link="input" register="false" transfer="false" optional="false" type="data" size="220179627"/>
    <uses file="Seismogram_FFI_0_2_ID00040.grm" link="output" register="false" transfer="false" optional="false" type="data" size="24000"/>
  </job>
  <job id="ID00041" namespace="CyberShake" name="PeakValCalcOkaya" version="1.0" runtime="0.71">
    <uses file="Seismogram_FFI_0_2_ID00040.grm" link="input" register="false" transfer="false" optional="false" type="data" size="24000"/>
    <uses file="PeakVals_FFI_0_2_ID00040.bsa" link="output" register="false" transfer="false" optional="false" type="data" size="216"/>
  </job>
  <job id="ID00042" namespace="CyberShake" name="SeismogramSynthesis" version="1.0" runtime="49.04">
    <uses file="FFI_0_2_txt.variation-s00863-h08404" link="input" register="true" transfer="true" optional="false" type="data" size="2609031"/>
    <uses file="FFI_0_2_subfx.sgt" link="input" register="false" transfer="false" optional="false" type="data" size="167166649"/>
    <uses file="FFI_0_2_subfy.sgt" link="input" register="false" transfer="false" optional="false" type="data" size="167166649"/>
    <uses file="Seismogram_FFI_0_2_ID00042.grm" link="output" register="false" transfer="false" optional="false" type="data" size="24000"/>
  </job>
  <job id="ID00043" namespace="CyberShake" name="PeakValCalcOkaya" version="1.0" runtime="1.35">
    <uses file="Seismogram_FFI_0_2_ID00042.grm" link="input" register="false" transfer="false" optional="false" type="data" size="24000"/>
    <uses file="PeakVals_FFI_0_2_ID00042.bsa" link="output" register="false" transfer="false" optional="false" type="data" size="216"/>
  </job>
  <job id="ID00044" namespace="CyberShake" name="SeismogramSynthesis" version="1.0" runtime="45.63">
    <uses file="FFI_0_2_txt.variation-s05812-h01901" link="input" register="true" transfer="true" optional="false" type="data" size="3903136"/>
    <uses file="FFI_0_2_subfx.sgt" link="input" register="false" transfer="false" optional="false" type="data" size="237234338"/>
    <uses file="FFI_0_2_subfy.sgt" link="input" register="false" transfer="false" optional="false" type="data" size="237234338"/>
    <uses file="Seismogram_FFI_0_2_ID00044.grm" link="output" register="false" transfer="false" optional="false" type="data" size="24000"/>
  </job>
  <job id="ID00045" namespace="CyberShake" name="PeakValCalcOkaya" version="1.0" runtime="0.78">
    <uses file="Seismogram_FFI_0_2_ID00044.grm" link="input" register="false" transfer="false" optional="false" type="data" size="24000"/>
    <uses file="PeakVals_FFI_0_2_ID00044.bsa" link="output" register="false" transfer="false" optional="false" type="data" size="216"/>
  </job>
  <job id="ID00046" namespace="CyberShake" name="SeismogramSynthesis" version="1.0" runtime="29.87">
    <uses file="FFI_0_2_txt.variation-s07440-h06759" link="input" register="true" transfer="true" optional="false" type="data" size="4583843"/>
    <uses file="FFI_0_2_subfx.sgt" link="input" register="false" transfer="false" optional="false" type="data" size="209194360"/>
    <uses file="FFI_0_2_subfy.sgt" link="input" register="false" transfer="false" optional="false" type="data" size="209194360"/>
    <uses file="Seismogram_FFI_0_2_ID00046.grm" link="output" register="false" transfer="false" optional="false" type="data" size="24000"/>
  </job>
  <job id="ID00047" namespace="CyberShake" name="PeakValCalcOkaya" version="1.0" runtime="1.43">
    <uses file="Seismogram_FFI_0_2_ID00046.grm" link="input" register="false" transfer="false" optional="false" type="data" size="24000"/>
    <uses file="PeakVals_FFI_0_2_ID00046.bsa" link="output" register="false" transfer="false" optional="false" type="data" size="216"/>
  </job>
  <job id="ID00048" namespace="CyberShake" name="SeismogramSynthesis" version="1.0" runtime="23.53">
    <uses file="FFI_0_2_txt.variation-s02876-h04258" link="input" register="true" transfer="true" optional="false" type="data" size="4901632"/>
    <uses file="FFI_0_2_subfx.sgt" link="input" register="false" transfer="false" optional="false" type="data" size="183315939"/>
    <uses file="FFI_0_2_subfy.sgt" link="input" register="false" transfer="false" optional="false" type="data" size="183315939"/>
    <uses file="Seismogram_FFI_0_2_ID00048.grm" link="output" register="false" transfer="false" optional="false" type="data" size="24000"/>
  </job>
  <job id="ID00049" namespace="CyberShake" name="PeakValCalcOkaya" version="1.0" runtime="0.57">
    <uses file="Seismogram_FFI_0_2_ID00048.grm" link="input" register="false" transfer="false" optional="false" type="data" size="24000"/>
    <uses file="PeakVals_FFI_0_2_ID00048.bsa" link="output" register="false" transfer="false" optional="false" type="data" size="216"/>
  </job>
<!-- part 3: list of control-flow dependencies (may be empty) -->
  <child ref="ID00000">
    <parent ref="ID00006"/>
    <parent ref="ID00039"/>
    <parent ref="ID00016"/>
    <parent ref="ID00027"/>
    <parent ref="ID00049"/>
    <parent ref="ID00004"/>
    <parent ref="ID00037"/>
    <parent ref="ID00014"/>
    <parent ref="ID00025"/>
    <parent ref="ID00047"/>
    <parent ref="ID00008"/>
    <parent ref="ID00018"/>
    <parent ref="ID00029"/>
    <parent ref="ID00020"/>
    <parent ref="ID00031"/>
    <parent ref="ID00041"/>
    <parent ref="ID00035"/>
    <parent ref="ID00012"/>
    <parent ref="ID00045"/>
    <parent ref="ID00022"/>
    <parent ref="ID00033"/>
    <parent ref="ID00010"/>
    <parent ref="ID00043"/>
  </child>
  <child ref="ID00001">
    <parent ref="ID00017"/>
    <parent ref="ID00028"/>
    <parent ref="ID00005"/>
    <parent ref="ID00038"/>
    <parent ref="ID00015"/>
    <parent ref="ID00026"/>
    <parent ref="ID00048"/>
    <parent ref="ID00003"/>
    <parent ref="ID00036"/>
    <parent ref="ID00009"/>
    <parent ref="ID00019"/>
    <parent ref="ID00007"/>
    <parent ref="ID00042"/>
    <parent ref="ID00030"/>
    <parent ref="ID00040"/>
    <parent ref="ID00013"/>
    <parent ref="ID00024"/>
    <parent ref="ID00046"/>
    <parent ref="ID00034"/>
    <parent ref="ID00011"/>
    <parent ref="ID00044"/>
    <parent ref="ID00021"/>
    <parent ref="ID00032"/>
  </child>
  <child ref="ID00003">
    <parent ref="ID00002"/>
  </child>
  <child ref="ID00004">
    <parent ref="ID00003"/>
  </child>
  <child ref="ID00005">
    <parent ref="ID00002"/>
  </child>
  <child ref="ID00006">
    <parent ref="ID00005"/>
  </child>
  <child ref="ID00007">
    <parent ref="ID00002"/>
  </child>
  <child ref="ID00008">
    <parent ref="ID00007"/>
  </child>
  <child ref="ID00009">
    <parent ref="ID00002"/>
  </child>
  <child ref="ID00010">
    <parent ref="ID00009"/>
  </child>
  <child ref="ID00011">
    <parent ref="ID00002"/>
  </child>
  <child ref="ID00012">
    <parent ref="ID00011"/>
  </child>
  <child ref="ID00013">
    <parent ref="ID00002"/>
  </child>
  <child ref="ID00014">
    <parent ref="ID00013"/>
  </child>
  <child ref="ID00015">
    <parent ref="ID00002"/>
  </child>
  <child ref="ID00016">
    <parent ref="ID00015"/>
  </child>
  <child ref="ID00017">
    <parent ref="ID00002"/>
  </child>
  <child ref="ID00018">
    <parent ref="ID00017"/>
  </child>
  <child ref="ID00019">
    <parent ref="ID00002"/>
  </child>
  <child ref="ID00020">
    <parent ref="ID00019"/>
  </child>
  <child ref="ID00021">
    <parent ref="ID00002"/>
  </child>
  <child ref="ID00022">
    <parent ref="ID00021"/>
  </child>
  <child ref="ID00024">
    <parent ref="ID00023"/>
  </child>
  <child ref="ID00025">
    <parent ref="ID00024"/>
  </child>
  <child ref="ID00026">
    <parent ref="ID00023"/>
  </child>
  <child ref="ID00027">
    <parent ref="ID00026"/>
  </child>
  <child ref="ID00028">
    <parent ref="ID00023"/>
  </child>
  <child ref="ID00029">
    <parent ref="ID00028"/>
  </child>
  <child ref="ID00030">
    <parent ref="ID00023"/>
  </child>
  <child ref="ID00031">
    <parent ref="ID00030"/>
  </child>
  <child ref="ID00032">
    <parent ref="ID00023"/>
  </child>
  <child ref="ID00033">
    <parent ref="ID00032"/>
  </child>
  <child ref="ID00034">
    <parent ref="ID00023"/>
  </child>
  <child ref="ID00035">
    <parent ref="ID00034"/>
  </child>
  <child ref="ID00036">
    <parent ref="ID00023"/>
  </child>
  <child ref="ID00037">
    <parent ref="ID00036"/>
  </child>
  <child ref="ID00038">
    <parent ref="ID00023"/>
  </child>
  <child ref="ID00039">
    <parent ref="ID00038"/>
  </child>
  <child ref="ID00040">
    <parent ref="ID00023"/>
  </child>
  <child ref="ID00041">
    <parent ref="ID00040"/>
  </child>
  <child ref="ID00042">
    <parent ref="ID00023"/>
  </child>
  <child ref="ID00043">
    <parent ref="ID00042"/>
  </child>
  <child ref="ID00044">
    <parent ref="ID00023"/>
  </child>
  <child ref="ID00045">
    <parent ref="ID00044"/>
  </child>
  <child ref="ID00046">
    <parent ref="ID00023"/>
  </child>
  <child ref="ID00047">
    <parent ref="ID00046"/>
  </child>
  <child ref="ID00048">
    <parent ref="ID00023"/>
  </child>
  <child ref="ID00049">
    <parent ref="ID00048"/>
  </child>
</adag>
